{
  "lastUpdated": "2026-06-21 10:02:46",
  "totalJobs": 264,
  "jobs": [
    {
      "source": "SarkariResult",
      "title": "PDC Bank Recruitment 2026 – Apply Online 147 Clerk, Officer",
      "posts": "Various Posts",
      "qualification": "N/A",
      "lastDate": "28 June 2026",
      "link": "https://www.sarkariresult.app/pdcc-bank-recruitment/",
      "scrapedAt": "2026-06-21 10:02:46"
    },
    {
      "source": "SarkariResult",
      "title": "NCRA Administrative Officer E Recruitment 2026 – Apply Online",
      "posts": "01 Post",
      "qualification": "N/A",
      "lastDate": "30 June 2026",
      "link": "https://www.sarkariresult.app/ncra-administrative-officer-e-recruitment-2026/",
      "scrapedAt": "2026-06-21 10:02:46"
    },
    {
      "source": "SarkariResult",
      "title": "WII Technical Assistant Recruitment 2026 Out – Apply Online",
      "posts": "50 Posts",
      "qualification": "N/A",
      "lastDate": "",
      "link": "https://www.sarkariresult.app/wii-technical-assistant-recruitment/",
      "scrapedAt": "2026-06-21 10:02:46"
    },
    {
      "source": "SarkariResult",
      "title": "JIPMER Group A Non-Faculty Recruitment 2026 Out – Apply Online",
      "posts": "34 Posts",
      "qualification": "N/A",
      "lastDate": "1 July 2026",
      "link": "https://www.sarkariresult.app/jipmer-group-a-non-faculty-recruitment-2026-out-apply-online-34-posts/",
      "scrapedAt": "2026-06-21 10:02:46"
    },
    {
      "source": "SarkariResult",
      "title": "UPSRLM Various Post Recruitment 2026 Out – Online Form",
      "posts": "3447 Posts",
      "qualification": "N/A",
      "lastDate": "1 July 2026",
      "link": "https://www.sarkariresult.app/upsrlm-various-post-online-form/",
      "scrapedAt": "2026-06-21 10:02:46"
    },
    {
      "source": "SarkariResult",
      "title": "Delhi Govt School Admission 2026 Online Registration For",
      "posts": "Class 6-9",
      "qualification": "N/A",
      "lastDate": "25 July 2026",
      "link": "https://www.sarkariresult.app/delhi-govt-school-admission-2026-online-registration-for-class-6-9/",
      "scrapedAt": "2026-06-21 10:02:46"
    },
    {
      "source": "SarkariResult",
      "title": "GBPUAT Dean Recruitment 2026 – Apply Now",
      "posts": "10 Posts",
      "qualification": "N/A",
      "lastDate": "25 June 2026",
      "link": "https://www.sarkariresult.app/gbpuat-dean-recruitment/",
      "scrapedAt": "2026-06-21 10:02:46"
    },
    {
      "source": "SarkariResult",
      "title": "CVC Recruitment 2026 – Apply Now Technical Examiner, Staff Car Driver",
      "posts": "06 Posts",
      "qualification": "N/A",
      "lastDate": "21 July 2026",
      "link": "https://www.sarkariresult.app/cvc-recruitment-2026-apply-now-technical-examiner-staff-car-driver-06-posts/",
      "scrapedAt": "2026-06-21 10:02:46"
    },
    {
      "source": "SarkariResult",
      "title": "TIFR Recruitment 2026 Out – Apply Online",
      "posts": "35 Posts",
      "qualification": "N/A",
      "lastDate": "4 July 2026",
      "link": "https://www.sarkariresult.app/tifr-recruitment-2026-out/",
      "scrapedAt": "2026-06-21 10:02:46"
    },
    {
      "source": "SarkariResult",
      "title": "HSSC Common Eligibility Test CET Group D Online Form 2026 Link Download",
      "posts": "Notification PDF",
      "qualification": "N/A",
      "lastDate": "3 July 2026",
      "link": "https://www.sarkariresult.app/hssc-common-eligibility-test-cet-group-d-online-form-2026-link-download-notification-pdf/",
      "scrapedAt": "2026-06-21 10:02:46"
    },
    {
      "source": "SarkariResult",
      "title": "UPSSSC Forest Guard Recruitment 2026 Out – Apply Online for",
      "posts": "708 Posts",
      "qualification": "N/A",
      "lastDate": "20 July 2026",
      "link": "https://www.sarkariresult.app/upsssc-forest-guard-recruitment-2026-out-apply-online-for-708-posts/",
      "scrapedAt": "2026-06-21 10:02:46"
    },
    {
      "source": "SarkariResult",
      "title": "TGPSC Deputy Educational Officers / Head Master Recruitment 2026 Out – Apply Online",
      "posts": "24 Posts",
      "qualification": "N/A",
      "lastDate": "19 July 2026",
      "link": "https://www.sarkariresult.app/tgpsc-deputy-educational-officers-head-master-recruitment-2026-out-apply-online-24-posts/",
      "scrapedAt": "2026-06-21 10:02:46"
    },
    {
      "source": "SarkariResult",
      "title": "MPSC Upper Divisional Clerk Recruitment 2026 Out – Online Form",
      "posts": "18 Posts",
      "qualification": "N/A",
      "lastDate": "24 July 2026",
      "link": "https://www.sarkariresult.app/mpsc-upper-divisional-clerk-recruitment-2026-out-online-form-18-posts/",
      "scrapedAt": "2026-06-21 10:02:46"
    },
    {
      "source": "SarkariResult",
      "title": "CSIR NPL Technician Recruitment 2026 Out – Apply Online",
      "posts": "20 Vacancies",
      "qualification": "N/A",
      "lastDate": "30 June 2026",
      "link": "https://www.sarkariresult.app/csir-npl-jobs/",
      "scrapedAt": "2026-06-21 10:02:46"
    },
    {
      "source": "SarkariResult",
      "title": "CAT Recruitment 2026 – Apply Now 82 Junior Accountant, Accounts",
      "posts": "Officer Posts",
      "qualification": "N/A",
      "lastDate": "30 Days",
      "link": "https://www.sarkariresult.app/cat-central-administrative-tribunal/",
      "scrapedAt": "2026-06-21 10:02:46"
    },
    {
      "source": "SarkariResult",
      "title": "RPSC APO Recruitment 2026 Out – Apply Online",
      "posts": "371 Posts",
      "qualification": "N/A",
      "lastDate": "7 July 2026",
      "link": "https://www.sarkariresult.app/rpsc-apo-recruitment-2026-out/",
      "scrapedAt": "2026-06-21 10:02:46"
    },
    {
      "source": "SarkariResult",
      "title": "Sports Authority of India Assistant Coach Recruitment 2026 OUT – Apply Online",
      "posts": "100 Posts",
      "qualification": "N/A",
      "lastDate": "27 June 2026",
      "link": "https://www.sarkariresult.app/sports-authority-of-india-sai/",
      "scrapedAt": "2026-06-21 10:02:46"
    },
    {
      "source": "SarkariResult",
      "title": "NPCIL KKNPP Stipendiary Trainee Recruitment 2026 Out – Apply Online",
      "posts": "255 Posts",
      "qualification": "N/A",
      "lastDate": "29 June 2026",
      "link": "https://www.sarkariresult.app/npcil-kknpp/",
      "scrapedAt": "2026-06-21 10:02:46"
    },
    {
      "source": "SarkariResult",
      "title": "DSSSB TGT Computer Science Recruitment 2026 Apply Online Out –",
      "posts": "675 Posts",
      "qualification": "N/A",
      "lastDate": "15 July 2026",
      "link": "https://www.sarkariresult.app/dsssb-tgt-computer-science-recruitment/",
      "scrapedAt": "2026-06-21 10:02:46"
    },
    {
      "source": "SarkariResult",
      "title": "RRB Technician Recruitment 2026 Out – Apply Online",
      "posts": "6565 Posts",
      "qualification": "N/A",
      "lastDate": "29 July 2026",
      "link": "https://www.sarkariresult.app/rrb-technician-2026/",
      "scrapedAt": "2026-06-21 10:02:46"
    },
    {
      "source": "SarkariResult",
      "title": "Indian Navy Agniveer (Apprentice) Recruitment 01/2027 & 02/2027 Out –",
      "posts": "Apply Online",
      "qualification": "N/A",
      "lastDate": "29 June 2026",
      "link": "https://www.sarkariresult.app/indian-navy-agniveer-apprentice-recruitment/",
      "scrapedAt": "2026-06-21 10:02:46"
    },
    {
      "source": "SarkariResult",
      "title": "IIT Kanpur Non Teaching Recruitment 2026 – Apply Online 80 JA, AEE and",
      "posts": "More Posts",
      "qualification": "N/A",
      "lastDate": "3 July 2026",
      "link": "https://www.sarkariresult.app/iit-kanpur-non-teaching-recruitment/",
      "scrapedAt": "2026-06-21 10:02:46"
    },
    {
      "source": "SarkariResult",
      "title": "Konkan Railway Corporation Recruitment 2026 Out Walk-In Interview For",
      "posts": "36 Posts",
      "qualification": "N/A",
      "lastDate": "23 June 2026",
      "link": "https://www.sarkariresult.app/konkan-railway-corporation-recruitment/",
      "scrapedAt": "2026-06-21 10:02:46"
    },
    {
      "source": "SarkariResult",
      "title": "Surguja District Assistant Veterinary Field Officer Recruitment 2026 – Apply Now",
      "posts": "15 Posts",
      "qualification": "N/A",
      "lastDate": "23 June 2026",
      "link": "https://www.sarkariresult.app/surguja-district/",
      "scrapedAt": "2026-06-21 10:02:46"
    },
    {
      "source": "SarkariResult",
      "title": "RCFL Recruitment 2026 – Apply Now 46 Honorary Doctors & Panel",
      "posts": "Doctors Posts",
      "qualification": "N/A",
      "lastDate": "31 July 2026",
      "link": "https://www.sarkariresult.app/rashtriya-chemicals-and-fertilizers-limited-rcfl/",
      "scrapedAt": "2026-06-21 10:02:46"
    },
    {
      "source": "SarkariResult",
      "title": "NEIGRIHMS Faculty Recruitment 2026 – Apply Now",
      "posts": "52 Posts",
      "qualification": "N/A",
      "lastDate": "22 June 2026",
      "link": "https://www.sarkariresult.app/neigrihms-group-a-faculty-recruitment/",
      "scrapedAt": "2026-06-21 10:02:46"
    },
    {
      "source": "SarkariResult",
      "title": "BSNL JTO Recruitment 2026 Out – Apply Online for 100 Junior Telecom",
      "posts": "Officer Posts",
      "qualification": "N/A",
      "lastDate": "3 July 2026",
      "link": "https://www.sarkariresult.app/bsnl-jto-jobs/",
      "scrapedAt": "2026-06-21 10:02:46"
    },
    {
      "source": "SarkariResult",
      "title": "Assam University Teaching Recruitment 2026 – Apply Online 123 Professor & Assistant",
      "posts": "Professor Posts",
      "qualification": "N/A",
      "lastDate": "10 July 2026",
      "link": "https://www.sarkariresult.app/assam-university-teaching-recruitment/",
      "scrapedAt": "2026-06-21 10:02:46"
    },
    {
      "source": "SarkariResult",
      "title": "CISF ASI Para Medical Staff Recruitment 2026 Notification Out – Apply Online Starts For",
      "posts": "24 Posts",
      "qualification": "N/A",
      "lastDate": "7 July 2026",
      "link": "https://www.sarkariresult.app/cisf-asi-para-medical-staff-recruitment-2026-notification-out/",
      "scrapedAt": "2026-06-21 10:02:46"
    },
    {
      "source": "SarkariResult",
      "title": "SCDRC Chandigarh Steno-Typist Recruitment 2026 – Apply Online",
      "posts": "01 Post",
      "qualification": "N/A",
      "lastDate": "24 June 2026",
      "link": "https://www.sarkariresult.app/scdrc-chandigarh-steno-typist-recruitment/",
      "scrapedAt": "2026-06-21 10:02:46"
    },
    {
      "source": "SarkariResult",
      "title": "SVPNPA Recruitment 2026 Out – Staff Nurse, Laboratory Technician and",
      "posts": "More Posts",
      "qualification": "N/A",
      "lastDate": "21 June 2026",
      "link": "https://www.sarkariresult.app/svpnpa-staff-nurse-laboratory-technician-and-more-posts/",
      "scrapedAt": "2026-06-21 10:02:46"
    },
    {
      "source": "SarkariResult",
      "title": "BSSA Recruitment 2026 – Apply Online 17 Doctor, Yoga Instructor and",
      "posts": "More Posts",
      "qualification": "N/A",
      "lastDate": "21 June 2026",
      "link": "https://www.sarkariresult.app/bssa-recruitment-2026/",
      "scrapedAt": "2026-06-21 10:02:46"
    },
    {
      "source": "SarkariResult",
      "title": "AAICLAS Assistant (Security) Recruitment 2026 – Apply Online",
      "posts": "62 Posts",
      "qualification": "N/A",
      "lastDate": "2 July 2026",
      "link": "https://www.sarkariresult.app/aaiclas-assistant-security-recruitment/",
      "scrapedAt": "2026-06-21 10:02:46"
    },
    {
      "source": "SarkariResult",
      "title": "GSRTC Driver Recruitment 2026 Notification Out – Apply Online",
      "posts": "4599 Posts",
      "qualification": "N/A",
      "lastDate": "5 July 2026",
      "link": "https://www.sarkariresult.app/gsrtc-conductor-and-driver-bharti/",
      "scrapedAt": "2026-06-21 10:02:46"
    },
    {
      "source": "SarkariResult",
      "title": "GSRTC Conductor Recruitment 2026 Notification Out – Online Form",
      "posts": "4318 Posts",
      "qualification": "N/A",
      "lastDate": "5 July 2026",
      "link": "https://www.sarkariresult.app/gsrtc-recruitment/",
      "scrapedAt": "2026-06-21 10:02:46"
    },
    {
      "source": "SarkariResult",
      "title": "PSPCL CRA 314/26 Recruitment 2026 – Apply Online 116 Fireman, Electrician and",
      "posts": "More Posts",
      "qualification": "N/A",
      "lastDate": "1 July 2026",
      "link": "https://www.sarkariresult.app/pspcl-cra-314-26-recruitment/",
      "scrapedAt": "2026-06-21 10:02:46"
    },
    {
      "source": "SarkariResult",
      "title": "UP Board Class 10th, 12th Compartment Online Form 2026",
      "posts": "Direct Link",
      "qualification": "N/A",
      "lastDate": "27 June 2026",
      "link": "https://www.sarkariresult.app/up-board-class-10th-12th-compartment-online-form/",
      "scrapedAt": "2026-06-21 10:02:46"
    },
    {
      "source": "SarkariResult",
      "title": "NHSRCL Recruitment 2026 Out – 15 IT, Safety, Data Analytics &",
      "posts": "Cloud Posts",
      "qualification": "N/A",
      "lastDate": "9 July 2026",
      "link": "https://www.sarkariresult.app/nhsrcl-jobs-apply-now/",
      "scrapedAt": "2026-06-21 10:02:46"
    },
    {
      "source": "SarkariResult",
      "title": "Kerala CSEB Recruitment 2026 – Apply Online 133 DEO, Junior Clerk and",
      "posts": "More Posts",
      "qualification": "N/A",
      "lastDate": "30 June 2026",
      "link": "https://www.sarkariresult.app/kerala-cseb-recruitment/",
      "scrapedAt": "2026-06-21 10:02:46"
    },
    {
      "source": "SarkariResult",
      "title": "ICDS (TP) Car Nicobar Data Entry Operator Recruitment 2026 –",
      "posts": "Apply Now",
      "qualification": "N/A",
      "lastDate": "25 June 2026",
      "link": "https://www.sarkariresult.app/icds-tp-car-nicobar-data-entry-operator-recruitment/",
      "scrapedAt": "2026-06-21 10:02:46"
    },
    {
      "source": "SarkariResult",
      "title": "Amethi BC Sakhi Recruitment 2026 OUT – 166 Gram",
      "posts": "Panchayat Posts",
      "qualification": "N/A",
      "lastDate": "30 June 2026",
      "link": "https://www.sarkariresult.app/amethi-bc-sakhi/",
      "scrapedAt": "2026-06-21 10:02:46"
    },
    {
      "source": "SarkariResult",
      "title": "SECL Tele-com./Radio Mechanic T&S Recruitment 2026 – Apply Online",
      "posts": "65 Posts",
      "qualification": "N/A",
      "lastDate": "1 July 2026",
      "link": "https://www.sarkariresult.app/secl-tele-com-radio-mechanic-ts-recruitment/",
      "scrapedAt": "2026-06-21 10:02:46"
    },
    {
      "source": "SarkariResult",
      "title": "MEA Section Officer Recruitment 2026 – Apply Now",
      "posts": "60 Posts",
      "qualification": "N/A",
      "lastDate": "17 July 2026",
      "link": "https://www.sarkariresult.app/mea-recruitment/",
      "scrapedAt": "2026-06-21 10:02:46"
    },
    {
      "source": "SarkariResult",
      "title": "Central University of Kerala Teaching Recruitment 2026 Out – Apply Online",
      "posts": "48 Posts",
      "qualification": "N/A",
      "lastDate": "10 July 2026",
      "link": "https://www.sarkariresult.app/central-university-of-kerala/",
      "scrapedAt": "2026-06-21 10:02:46"
    },
    {
      "source": "SarkariResult",
      "title": "CMO Mathura Medical Officer Recruitment 2026 – Walk in",
      "posts": "20 Posts",
      "qualification": "N/A",
      "lastDate": "30 June 2026",
      "link": "https://www.sarkariresult.app/cmo-mathura-medical-officer-recruitment/",
      "scrapedAt": "2026-06-21 10:02:46"
    },
    {
      "source": "SarkariResult",
      "title": "DHS Vellore Recruitment 2026 – Apply 43 Medical Officer, Driver and",
      "posts": "More Posts",
      "qualification": "N/A",
      "lastDate": "26 June 2026",
      "link": "https://www.sarkariresult.app/dhs-vellore-recruitment-2026-apply-43-medical-officer-driver-and-more-posts/",
      "scrapedAt": "2026-06-21 10:02:46"
    },
    {
      "source": "SarkariResult",
      "title": "District Collector Krishnagiri Law Officers Recruitment 2026 – Apply Now",
      "posts": "11 Posts",
      "qualification": "N/A",
      "lastDate": "30 June 2026",
      "link": "https://www.sarkariresult.app/district-collector-krishnagiri-law-officers-recruitment/",
      "scrapedAt": "2026-06-21 10:02:46"
    },
    {
      "source": "SarkariResult",
      "title": "SAIL BSL Young Professional Recruitment 2026 Out – Apply Online",
      "posts": "20 Posts",
      "qualification": "N/A",
      "lastDate": "1 July 2026",
      "link": "https://www.sarkariresult.app/sail-bsl-young-professional-recruitment/",
      "scrapedAt": "2026-06-21 10:02:46"
    },
    {
      "source": "SarkariResult",
      "title": "Bank of Baroda Recruitment 2026 – Apply Various Manager",
      "posts": "86 Posts",
      "qualification": "N/A",
      "lastDate": "6 July 2026",
      "link": "https://www.sarkariresult.app/bank-of-baroda-recruitment-2026/",
      "scrapedAt": "2026-06-21 10:02:46"
    },
    {
      "source": "SarkariResult",
      "title": "APMSRB Recruitment 2026 – Staff Nurse, Pharmacist & Multi Rehabilitation Worker",
      "posts": "529 Posts",
      "qualification": "N/A",
      "lastDate": "30 June 2026",
      "link": "https://www.sarkariresult.app/nhm-contract-posts-notification/",
      "scrapedAt": "2026-06-21 10:02:46"
    },
    {
      "source": "SarkariResult",
      "title": "Odisha Police OSSF Ex-Servicemen Recruitment 2026 OUT – 120",
      "posts": "Technical Posts",
      "qualification": "N/A",
      "lastDate": "1 July 2026",
      "link": "https://www.sarkariresult.app/odisha-police-ossf-ex-servicemen-recruitment-2026-out-120-technical-posts/",
      "scrapedAt": "2026-06-21 10:02:46"
    },
    {
      "source": "SarkariResult",
      "title": "IIT Dharwad Non Teaching Recruitment 2026 – Apply Online Asst Registrar,",
      "posts": "JA Posts",
      "qualification": "N/A",
      "lastDate": "13 July 2026",
      "link": "https://www.sarkariresult.app/iit-dharwad-non-teaching-recruitment/",
      "scrapedAt": "2026-06-21 10:02:46"
    },
    {
      "source": "SarkariResult",
      "title": "ACMS Recruitment 2026 – Apply Online Lower Division Clerk, Dissection Hall",
      "posts": "Attendant Posts",
      "qualification": "N/A",
      "lastDate": "22 June 2026",
      "link": "https://www.sarkariresult.app/acms-recruitment/",
      "scrapedAt": "2026-06-21 10:02:46"
    },
    {
      "source": "SarkariResult",
      "title": "PPSC Punjab Civil Services Recruitment 2026 Out – Apply Online",
      "posts": "26 Posts",
      "qualification": "N/A",
      "lastDate": "30 June 2026",
      "link": "https://www.sarkariresult.app/ppsc-pcs-recruitment/",
      "scrapedAt": "2026-06-21 10:02:46"
    },
    {
      "source": "SarkariResult",
      "title": "EIL Associate Engineer Recruitment 2026 – Apply Online",
      "posts": "41 Posts",
      "qualification": "N/A",
      "lastDate": "30 June 2026",
      "link": "https://www.sarkariresult.app/eil-associate-engineer-recruitment-2026-apply-online-41-posts/",
      "scrapedAt": "2026-06-21 10:02:46"
    },
    {
      "source": "SarkariResult",
      "title": "Rajendra University Balangir Teaching Posts Recruitment 2026 – Apply Now",
      "posts": "17 Posts",
      "qualification": "N/A",
      "lastDate": "25 June 2026",
      "link": "https://www.sarkariresult.app/rajendra-university-balangir-teaching-posts/",
      "scrapedAt": "2026-06-21 10:02:46"
    },
    {
      "source": "SarkariResult",
      "title": "MPSC Group C Recruitment 2026 Notification Out – Apply Online 20 Bailiff and",
      "posts": "Clerk Posts",
      "qualification": "N/A",
      "lastDate": "7 July 2026",
      "link": "https://www.sarkariresult.app/mpsc-group-c-recruitment-2026-notification-out-apply-online-20-bailiff-and-clerk-posts/",
      "scrapedAt": "2026-06-21 10:02:46"
    },
    {
      "source": "SarkariResult",
      "title": "Vijayapura Municipal Corporation Civil Servant Recruitment 2026 Out –",
      "posts": "118 Posts",
      "qualification": "N/A",
      "lastDate": "25 June 2026",
      "link": "https://www.sarkariresult.app/vijayapura-municipal-corporation/",
      "scrapedAt": "2026-06-21 10:02:46"
    },
    {
      "source": "SarkariResult",
      "title": "APSSB CHSLE Recruitment 2026 Out – Apply Online 207 Group",
      "posts": "C Posts",
      "qualification": "N/A",
      "lastDate": "10 August 2026",
      "link": "https://www.sarkariresult.app/apssb-chsle-recruitment/",
      "scrapedAt": "2026-06-21 10:02:46"
    },
    {
      "source": "SarkariResult",
      "title": "SSC SSA/UDC LDCE 2025 Notification Out – Online Apply 227 Group",
      "posts": "C Posts",
      "qualification": "N/A",
      "lastDate": "26 June 2026",
      "link": "https://www.sarkariresult.app/ssc-ssa-udc-ldce-2025-notification-out-online-apply-227-group-c-posts/",
      "scrapedAt": "2026-06-21 10:02:46"
    },
    {
      "source": "SarkariResult",
      "title": "KSP Civil Police Constable Recruitment 2026 Out – Apply Online",
      "posts": "3991 Posts",
      "qualification": "N/A",
      "lastDate": "3 July 2026",
      "link": "https://www.sarkariresult.app/ksp-civil-police-constable-recruitment/",
      "scrapedAt": "2026-06-21 10:02:46"
    },
    {
      "source": "SarkariResult",
      "title": "PSPCL ALM Advt No. CRA 318/26 Recruitment 2026 Cancelled– Apply Online",
      "posts": "3000 Posts",
      "qualification": "N/A",
      "lastDate": "6 July 2026",
      "link": "https://www.sarkariresult.app/pspcl-alm-advt-no-cra-318-26-recruitment-2026-apply-online-3000-posts/",
      "scrapedAt": "2026-06-21 10:02:46"
    },
    {
      "source": "SarkariResult",
      "title": "Central Bank of India Apprentice Recruitment 2026 – Apply Online",
      "posts": "4500 Posts",
      "qualification": "N/A",
      "lastDate": "22 June 2026",
      "link": "https://www.sarkariresult.app/central-bank-of-india-apprentice-recruitment-2025-apply-check-4500-posts/",
      "scrapedAt": "2026-06-21 10:02:46"
    },
    {
      "source": "SarkariResult",
      "title": "IIT Madras Assistant Professor Recruitment 2026 Out – Apply Online",
      "posts": "40 Posts",
      "qualification": "N/A",
      "lastDate": "15 October 2026",
      "link": "https://www.sarkariresult.app/iit-madras-faculty-recruitment/",
      "scrapedAt": "2026-06-21 10:02:46"
    },
    {
      "source": "SarkariResult",
      "title": "RBI Young Professional Recruitment 2026 Notification Out – Apply Online",
      "posts": "12 Posts",
      "qualification": "N/A",
      "lastDate": "6 July 2026",
      "link": "https://www.sarkariresult.app/rbi-young-professional-recruitment-2026-notification/",
      "scrapedAt": "2026-06-21 10:02:46"
    },
    {
      "source": "SarkariResult",
      "title": "UP DELEd Admission 2026 Registration Form, Fee, Date and",
      "posts": "Apply Process",
      "qualification": "N/A",
      "lastDate": "8 July 2026",
      "link": "https://www.sarkariresult.app/up-deled-admission-2026-registration-form-fee-date-and-apply-process/",
      "scrapedAt": "2026-06-21 10:02:46"
    },
    {
      "source": "SarkariResult",
      "title": "Jharkhand JSSC JTGLCCE Recruitment 2026 Out – Apply Online",
      "posts": "611 Posts",
      "qualification": "N/A",
      "lastDate": "30 June 2026",
      "link": "https://www.sarkariresult.app/jharkhand-jssc-jtglcce-jobs/",
      "scrapedAt": "2026-06-21 10:02:46"
    },
    {
      "source": "SarkariResult",
      "title": "Sikkim PSC Accounts Clerk / Junior Storekeeper Recruitment 2026 – Apply Online",
      "posts": "50 Posts",
      "qualification": "N/A",
      "lastDate": "31 July 2026",
      "link": "https://www.sarkariresult.app/sikkim-psc-accounts-clerk-junior-storekeeper-recruitment-2026-apply-online-50-posts/",
      "scrapedAt": "2026-06-21 10:02:46"
    },
    {
      "source": "SarkariResult",
      "title": "HPPSC Scientific Officer Recruitment 2026 Out –",
      "posts": "Apply Online",
      "qualification": "N/A",
      "lastDate": "7 July 2026",
      "link": "https://www.sarkariresult.app/hppsc-scientific-officer-recruitment-2026-out-apply-online/",
      "scrapedAt": "2026-06-21 10:02:46"
    },
    {
      "source": "SarkariResult",
      "title": "ISRO SDSC SHAR Teacher Recruitment 2026 – Apply Online 10 Trained Graduate Teacher, Primary",
      "posts": "Teacher Posts",
      "qualification": "N/A",
      "lastDate": "7 July 2026",
      "link": "https://www.sarkariresult.app/isro-sdsc-shar-teacher-recruitment-2026-apply-online-10-trained-graduate-teacher-primary-teacher-posts/",
      "scrapedAt": "2026-06-21 10:02:46"
    },
    {
      "source": "SarkariResult",
      "title": "GSSSB Junior Pharmacist Recruitment 2026 Notification Out  for 266 Posts",
      "posts": "Apply Online",
      "qualification": "N/A",
      "lastDate": "25 June 2026",
      "link": "https://www.sarkariresult.app/gsssb-junior-pharmacist-recruitment-2026-notification-out-for-266-posts-apply-online/",
      "scrapedAt": "2026-06-21 10:02:46"
    },
    {
      "source": "SarkariResult",
      "title": "HPPSC Assistant Professor Recruitment 2026 Notification Out – Online Form",
      "posts": "369 Posts",
      "qualification": "N/A",
      "lastDate": "14 July 2026",
      "link": "https://www.sarkariresult.app/hppsc-assistant-professor-recruitment-2026-notification/",
      "scrapedAt": "2026-06-21 10:02:46"
    },
    {
      "source": "SarkariResult",
      "title": "UCSL Workmen Recruitment 2026 Notification Out – Apply Online 35 Pipe Fitter, Welder,",
      "posts": "Electrician Posts",
      "qualification": "N/A",
      "lastDate": "17 July 2026",
      "link": "https://www.sarkariresult.app/ucsl-workmen-recruitment-2026-notification-out-apply-online-35-pipe-fitter-welder-electrician-posts/",
      "scrapedAt": "2026-06-21 10:02:46"
    },
    {
      "source": "SarkariResult",
      "title": "Samagra Shiksha Diu Recruitment 2026 For 22 Resource Person, Primary Teacher and",
      "posts": "More Posts",
      "qualification": "N/A",
      "lastDate": "1 July 2026",
      "link": "https://www.sarkariresult.app/samagra-shiksha-diu-recruitment-2026-for-22-resource-person-primary-teacher-and-more-posts/",
      "scrapedAt": "2026-06-21 10:02:46"
    },
    {
      "source": "SarkariResult",
      "title": "Tripura University Recruitment 2026 – Apply Now Internal Audit Officer and Assistant",
      "posts": "Registrar Posts",
      "qualification": "N/A",
      "lastDate": "29 June 2026",
      "link": "https://www.sarkariresult.app/tripura-university-recruitment/",
      "scrapedAt": "2026-06-21 10:02:46"
    },
    {
      "source": "SarkariResult",
      "title": "IPRCL Recruitment 2026 – Apply Now 15 Manager, Sr. Manager and",
      "posts": "More Posts",
      "qualification": "N/A",
      "lastDate": "24 June 2026",
      "link": "https://www.sarkariresult.app/iprcl-recruitment-2026-apply-now-15-manager-sr-manager-and-more-posts/",
      "scrapedAt": "2026-06-21 10:02:46"
    },
    {
      "source": "SarkariResult",
      "title": "ECHS Jharkhand Recruitment 2026 – Apply 21 Medical, Para Medical & Non Medical",
      "posts": "Staff Posts",
      "qualification": "N/A",
      "lastDate": "4 July 2026",
      "link": "https://www.sarkariresult.app/echs-jharkhand-recruitment/",
      "scrapedAt": "2026-06-21 10:02:46"
    },
    {
      "source": "SarkariResult",
      "title": "Sainik School Jhansi Recruitment 2026 – Apply Now PGT, Lab Assistant and",
      "posts": "More Posts",
      "qualification": "N/A",
      "lastDate": "26 June 2026",
      "link": "https://www.sarkariresult.app/sainik-school-jhansi-recruitment-2026/",
      "scrapedAt": "2026-06-21 10:02:46"
    },
    {
      "source": "SarkariResult",
      "title": "Ariyalur District Court Law Officer Recruitment 2026 – Apply Now",
      "posts": "15 Posts",
      "qualification": "N/A",
      "lastDate": "29 June 2026",
      "link": "https://www.sarkariresult.app/ariyalur-district-court/",
      "scrapedAt": "2026-06-21 10:02:46"
    },
    {
      "source": "SarkariResult",
      "title": "Northeast Frontier Railway Scouts and Guides Quota Recruitment 2026 – Apply Now",
      "posts": "22 Posts",
      "qualification": "N/A",
      "lastDate": "29 July 2026",
      "link": "https://www.sarkariresult.app/northeast-frontier-railway-scouts-and-guides-quota-recruitment-2026/",
      "scrapedAt": "2026-06-21 10:02:46"
    },
    {
      "source": "SarkariResult",
      "title": "Cabinet Secretariat Senior Field Officer Recruitment 2026 – Apply Now",
      "posts": "25 Posts",
      "qualification": "N/A",
      "lastDate": "12 July 2026",
      "link": "https://www.sarkariresult.app/cabinet-secretariat-senior-field-officer-recruitment/",
      "scrapedAt": "2026-06-21 10:02:46"
    },
    {
      "source": "SarkariResult",
      "title": "DSSSB 03/2026 Recruitment Out – Apply Online For 1979 Assistant, Trained Graduate Teacher",
      "posts": "Various Posts",
      "qualification": "N/A",
      "lastDate": "15 July 2026",
      "link": "https://www.sarkariresult.app/dsssb-03-2026/",
      "scrapedAt": "2026-06-21 10:02:46"
    },
    {
      "source": "SarkariResult",
      "title": "SAC ISRO Apprentice Recruitment 2026 OUT – Walk In Graduate, Technician & Trade",
      "posts": "Apprentice Posts",
      "qualification": "N/A",
      "lastDate": "3 July 2026",
      "link": "https://www.sarkariresult.app/sac-isro-apprentice-recruitment-2026/",
      "scrapedAt": "2026-06-21 10:02:46"
    },
    {
      "source": "SarkariResult",
      "title": "Indian Air Force Airmen Group Y Medical Assistant 02/2027 Recruitment –",
      "posts": "Apply Online",
      "qualification": "N/A",
      "lastDate": "26 July 2026",
      "link": "https://www.sarkariresult.app/indian-air-force-airmen-group-y-medical-assistant-02-2027/",
      "scrapedAt": "2026-06-21 10:02:46"
    },
    {
      "source": "SarkariResult",
      "title": "ICSIL DCCWS Helper/MTS Recruitment 2026 Out – Apply Online",
      "posts": "75 Posts",
      "qualification": "N/A",
      "lastDate": "25 June 2026",
      "link": "https://www.sarkariresult.app/icsil-dccws-helper-mts-recruitment/",
      "scrapedAt": "2026-06-21 10:02:46"
    },
    {
      "source": "SarkariResult",
      "title": "PSPCL ALM Recruitment 2026 Notification Out For 3289 Assistant Lineman",
      "posts": "Posts Cancelled",
      "qualification": "N/A",
      "lastDate": "6 July 2026",
      "link": "https://www.sarkariresult.app/pspcl-alm-advertisement-no-cra-317-26/",
      "scrapedAt": "2026-06-21 10:02:46"
    },
    {
      "source": "SarkariResult",
      "title": "Collector’s Office Chengalpattu Law Officer Recruitment 2026 – Apply Now",
      "posts": "20 Posts",
      "qualification": "N/A",
      "lastDate": "29 June 2026",
      "link": "https://www.sarkariresult.app/collectors-office-chengalpattu-law-officer-recruitment-2026/",
      "scrapedAt": "2026-06-21 10:02:46"
    },
    {
      "source": "SarkariResult",
      "title": "BAVMC Pune Recruitment 2026 – Walk in 45 Tutor, Junior & Senior",
      "posts": "Resident Posts",
      "qualification": "N/A",
      "lastDate": "24 June 2026",
      "link": "https://www.sarkariresult.app/bavmc-pune-recruitment/",
      "scrapedAt": "2026-06-21 10:02:46"
    },
    {
      "source": "SarkariResult",
      "title": "Punjab and Haryana High Court Recruitment 2026 Out – Apply Online 167 Safai Sewak,",
      "posts": "Mali Posts",
      "qualification": "N/A",
      "lastDate": "30 June 2026",
      "link": "https://www.sarkariresult.app/punjab-haryana-high-court-safai-sewak-mali-online-form-2026/",
      "scrapedAt": "2026-06-21 10:02:46"
    },
    {
      "source": "SarkariResult",
      "title": "DCPU Banka Support Person Recruitment 2026 – Apply Now",
      "posts": "20 Posts",
      "qualification": "N/A",
      "lastDate": "4 July 2026",
      "link": "https://www.sarkariresult.app/dcpu-banka-support-person-recruitment/",
      "scrapedAt": "2026-06-21 10:02:46"
    },
    {
      "source": "SarkariResult",
      "title": "UKSSSC AAO Recruitment 2026 Out – Apply Online 90 Asst Agriculture Officer, Fodder",
      "posts": "Assistant Posts",
      "qualification": "N/A",
      "lastDate": "21 June 2026",
      "link": "https://www.sarkariresult.app/uksssc-aao-recruitment/",
      "scrapedAt": "2026-06-21 10:02:46"
    },
    {
      "source": "SarkariResult",
      "title": "Indian Air Force Agniveervayu Intake 02/2027 Recruitment Out –",
      "posts": "Apply Online",
      "qualification": "N/A",
      "lastDate": "26 July 2026",
      "link": "https://www.sarkariresult.app/indian-air-force-agniveervayu-intake-02-2027-recruitment-out-apply-online/",
      "scrapedAt": "2026-06-21 10:02:46"
    },
    {
      "source": "SarkariResult",
      "title": "GSSSB Assistant Engineer (Mechanical) Recruitment 2026 – Apply Online",
      "posts": "110 Posts",
      "qualification": "N/A",
      "lastDate": "29 June 2026",
      "link": "https://www.sarkariresult.app/gsssb-assistant-engineer-mechanical-recruitment-2026/",
      "scrapedAt": "2026-06-21 10:02:46"
    },
    {
      "source": "SarkariResult",
      "title": "CGPSC ADPO Recruitment 2026 – Apply Online Assistant District Prosecution Officer",
      "posts": "15 Posts",
      "qualification": "N/A",
      "lastDate": "21 July 2026",
      "link": "https://www.sarkariresult.app/cgpsc-adpo-recruitment/",
      "scrapedAt": "2026-06-21 10:02:46"
    },
    {
      "source": "SarkariResult",
      "title": "JKSSB Recruitment 2026 Out – Apply Online 130 Electrician, Plumber and",
      "posts": "More Posts",
      "qualification": "N/A",
      "lastDate": "21 July 2026",
      "link": "https://www.sarkariresult.app/jkssb-vacancy-apply-online/",
      "scrapedAt": "2026-06-21 10:02:46"
    },
    {
      "source": "SarkariResult",
      "title": "Delhi Cantt Recruitment 2026 Out – Assistant Engineer, Junior",
      "posts": "Engineer Posts",
      "qualification": "N/A",
      "lastDate": "14 August 2026",
      "link": "https://www.sarkariresult.app/delhi-cantt-recruitment-2026-out/",
      "scrapedAt": "2026-06-21 10:02:46"
    },
    {
      "source": "SarkariResult",
      "title": "Rajasthan RPSC RAS Pre 2026 Notification Out – Online Form Link For",
      "posts": "607 Posts",
      "qualification": "N/A",
      "lastDate": "3 July 2026",
      "link": "https://www.sarkariresult.app/rpsc-ras-2026/",
      "scrapedAt": "2026-06-21 10:02:46"
    },
    {
      "source": "SarkariResult",
      "title": "AIIMS Jammu Non-Faculty Recruitment 2026 – Apply Online 29",
      "posts": "Technician Posts",
      "qualification": "N/A",
      "lastDate": "25 June 2026",
      "link": "https://www.sarkariresult.app/aiims-jammu-non-faculty-recruitment/",
      "scrapedAt": "2026-06-21 10:02:46"
    },
    {
      "source": "SarkariResult",
      "title": "Income Tax Department Sports Quota Recruitment 2026 – Apply 12 MTS, Steno, Tax",
      "posts": "Assistant Posts",
      "qualification": "N/A",
      "lastDate": "31 July 2026",
      "link": "https://www.sarkariresult.app/income-tax-department-sports-quota-recruitment-2026-apply-12-mts-steno-tax-assistant-posts/",
      "scrapedAt": "2026-06-21 10:02:46"
    },
    {
      "source": "SarkariResult",
      "title": "JK Bank Auditor Recruitment 2026 Out –",
      "posts": "Apply Online",
      "qualification": "N/A",
      "lastDate": "26 June 2026",
      "link": "https://www.sarkariresult.app/jk-bank-auditor-recruitment-2026-out-apply-online/",
      "scrapedAt": "2026-06-21 10:02:46"
    },
    {
      "source": "SarkariResult",
      "title": "MPPSC Recruitment 2026 Out – Apply Online 06 IAEO,",
      "posts": "AAO Posts",
      "qualification": "N/A",
      "lastDate": "3 September 2026",
      "link": "https://www.sarkariresult.app/mppsc-recruitment-2026-out-apply-online-06-iaeo-aao-posts/",
      "scrapedAt": "2026-06-21 10:02:46"
    },
    {
      "source": "SarkariResult",
      "title": "RPSC Assistant Prosecution Officer APO Recruitment 2026 OUT – Apply Online",
      "posts": "370 Posts",
      "qualification": "N/A",
      "lastDate": "7 July 2026",
      "link": "https://www.sarkariresult.app/rpsc-assistant-prosecution-officer-apo-recruitment/",
      "scrapedAt": "2026-06-21 10:02:46"
    },
    {
      "source": "SarkariResult",
      "title": "NBEMS NAT Board Group A, B, C Recruitment 2026 – Apply Online 53",
      "posts": "Various Post",
      "qualification": "N/A",
      "lastDate": "20 July 2026",
      "link": "https://www.sarkariresult.app/nbems-nat-board-group-a-b-c-recruitment-2026/",
      "scrapedAt": "2026-06-21 10:02:46"
    },
    {
      "source": "SarkariResult",
      "title": "MPESB PNST Admission Form 2026 – Apply Link Check",
      "posts": "Exam Dates",
      "qualification": "N/A",
      "lastDate": "23 June 2026",
      "link": "https://www.sarkariresult.app/mpesb-pnst-admission-form/",
      "scrapedAt": "2026-06-21 10:02:46"
    },
    {
      "source": "SarkariResult",
      "title": "Chacha Nehru Bal Chikitsalaya Recruitment 2026 – Apply Now 19 Teaching Faculty,",
      "posts": "MO Posts",
      "qualification": "N/A",
      "lastDate": "27 June 2026",
      "link": "https://www.sarkariresult.app/chacha-nehru-bal-chikitsalaya/",
      "scrapedAt": "2026-06-21 10:02:46"
    },
    {
      "source": "SarkariResult",
      "title": "UPSSSC Platoon Commander Recruitment 2026 – Apply Online",
      "posts": "295 Posts",
      "qualification": "N/A",
      "lastDate": "6 July 2026",
      "link": "https://www.sarkariresult.app/upsssc-platoon-commander-recruitment-2026-apply-online-295-posts/",
      "scrapedAt": "2026-06-21 10:02:46"
    },
    {
      "source": "SarkariResult",
      "title": "DHS Virudhunagar Recruitment 2026 – Apply Now 14 Medical Officer, Security Guard",
      "posts": "and More",
      "qualification": "N/A",
      "lastDate": "6 July 2026",
      "link": "https://www.sarkariresult.app/dhs-virudhunagar-recruitment/",
      "scrapedAt": "2026-06-21 10:02:46"
    },
    {
      "source": "SarkariResult",
      "title": "MMRCL Recruitment 2026 Out – Apply Online 24 Assistant, Jr Engineer and",
      "posts": "More Posts",
      "qualification": "N/A",
      "lastDate": "26 June 2026",
      "link": "https://www.sarkariresult.app/mmrcl-recruitment/",
      "scrapedAt": "2026-06-21 10:02:46"
    },
    {
      "source": "SarkariResult",
      "title": "ICSIL RGSSH Nursing Officer Recruitment 2026 Out – Apply Online",
      "posts": "65 Posts",
      "qualification": "N/A",
      "lastDate": "23 June 2026",
      "link": "https://www.sarkariresult.app/icsil-rgssh-nursing-officer-recruitment-2026-out-apply-online-65-posts/",
      "scrapedAt": "2026-06-21 10:02:46"
    },
    {
      "source": "SarkariResult",
      "title": "UPSSSC Excise Constable Recruitment 2026 Out Apply Online 722 Abkari",
      "posts": "Siphai Posts",
      "qualification": "N/A",
      "lastDate": "24 June 2026",
      "link": "https://www.sarkariresult.app/upsssc-excise-constable-recruitment-2026-out-apply-online-722-abkari-siphai-posts/",
      "scrapedAt": "2026-06-21 10:02:46"
    },
    {
      "source": "SarkariResult",
      "title": "NBEMS Recruitment 2026 Out – Apply Junior Assistant, Steno &",
      "posts": "More Posts",
      "qualification": "N/A",
      "lastDate": "29 June 2026",
      "link": "https://www.sarkariresult.app/nbems-recruitment/",
      "scrapedAt": "2026-06-21 10:02:46"
    },
    {
      "source": "SarkariResult",
      "title": "SBI PO Recruitment 2026 Out – Apply Online For",
      "posts": "1500 Vacancies",
      "qualification": "N/A",
      "lastDate": "8 July 2026",
      "link": "https://www.sarkariresult.app/sbi-po-recruitment-2026-out-apply-online-for-1500-vacancies/",
      "scrapedAt": "2026-06-21 10:02:46"
    },
    {
      "source": "SarkariResult",
      "title": "Sikkim PSC Warder Recruitment 2026 – Apply Online for",
      "posts": "37 Posts",
      "qualification": "N/A",
      "lastDate": "31 July 2026",
      "link": "https://www.sarkariresult.app/sikkim-psc-warder-recruitment-2026-apply-online-for-37-posts/",
      "scrapedAt": "2026-06-21 10:02:46"
    },
    {
      "source": "SarkariResult",
      "title": "SSC 10+2 CHSL 2025 Sample Option-cum-Preference Form For 3522 Posts",
      "posts": "Check Here",
      "qualification": "N/A",
      "lastDate": "",
      "link": "https://www.sarkariresult.app/ssc-chsl-recruitment-2025-apply-online-ldc-jsa-deo-pa-various-posts/",
      "scrapedAt": "2026-06-21 10:02:46"
    },
    {
      "source": "SarkariResult",
      "title": "UPSSSC Havaldar Instructor Recruitment 2026 Out for 209 Posts Apply",
      "posts": "All Details",
      "qualification": "N/A",
      "lastDate": "9 July 2026",
      "link": "https://www.sarkariresult.app/upsssc-havaldar-instructor-recruitment-2026-out-for-209-posts-apply-all-details/",
      "scrapedAt": "2026-06-21 10:02:46"
    },
    {
      "source": "SarkariResult",
      "title": "CERSAI Recruitment 2026 – Apply Online 16 Chief Manager, AGM and",
      "posts": "More Posts",
      "qualification": "N/A",
      "lastDate": "20 July 2026",
      "link": "https://www.sarkariresult.app/cersai-recruitment-2026-apply-online-16-chief-manager-agm-and-more-posts/",
      "scrapedAt": "2026-06-21 10:02:46"
    },
    {
      "source": "SarkariResult",
      "title": "MPPHSCL Recruitment 2026 OUT – Apply Online",
      "posts": "41 Posts",
      "qualification": "N/A",
      "lastDate": "25 June 2026",
      "link": "https://www.sarkariresult.app/madhya-pradesh-public-health-services-corporation-limited-mpphscl/",
      "scrapedAt": "2026-06-21 10:02:46"
    },
    {
      "source": "SarkariResult",
      "title": "IIT Hyderabad Non Teaching Recruitment 2026 – Apply Online",
      "posts": "21 Posts",
      "qualification": "N/A",
      "lastDate": "20 July 2026",
      "link": "https://www.sarkariresult.app/iit-hyderabad-non-teaching-job/",
      "scrapedAt": "2026-06-21 10:02:46"
    },
    {
      "source": "SarkariResult",
      "title": "PM SHRI School Jawahar Navodaya Vidyalaya Recruitment 2026 – 15 Lab Attendant, Caretaker Walk",
      "posts": "in Jobs",
      "qualification": "N/A",
      "lastDate": "30 June 2026",
      "link": "https://www.sarkariresult.app/pm-shri-school-jawahar-navodaya-vidyalaya-recruitment-2026-15-lab-attendant-caretaker-walk-in-jobs/",
      "scrapedAt": "2026-06-21 10:02:46"
    },
    {
      "source": "SarkariResult",
      "title": "TGPSC Recruitment 2026 Notification Out – Apply Online 86 Senior",
      "posts": "Lecturer Posts",
      "qualification": "N/A",
      "lastDate": "29 July 2026",
      "link": "https://www.sarkariresult.app/tgpsc-recruitment-2026-notification-out-apply-online-86-senior-lecturer-posts/",
      "scrapedAt": "2026-06-21 10:02:46"
    },
    {
      "source": "SarkariResult",
      "title": "CDB Recruitment 2026 – Apply Now 10 Senior Auditor, Assistant and",
      "posts": "More Posts",
      "qualification": "N/A",
      "lastDate": "28 July 2026",
      "link": "https://www.sarkariresult.app/coconut-development-board-cdb/",
      "scrapedAt": "2026-06-21 10:02:46"
    },
    {
      "source": "SarkariResult",
      "title": "ZSS Boudh Recruitment 2026 – Apply Mow 20 Medical Officer, Counsellor",
      "posts": "Various Posts",
      "qualification": "N/A",
      "lastDate": "4 July 2026",
      "link": "https://www.sarkariresult.app/zss-boudh-recruitment-2026-apply-mow-20-medical-officer-counsellor-various-posts/",
      "scrapedAt": "2026-06-21 10:02:46"
    },
    {
      "source": "SarkariResult",
      "title": "SBI Specialist Cadre Officer Recruitment 2026 –",
      "posts": "Online Apply",
      "qualification": "N/A",
      "lastDate": "8 July 2026",
      "link": "https://www.sarkariresult.app/sbi-specialist-cadre-officer-recruitment-2026/",
      "scrapedAt": "2026-06-21 10:02:46"
    },
    {
      "source": "SarkariResult",
      "title": "BMC Recruitment 2026 – Apply 29 Pharmacist, Technician and",
      "posts": "More Posts",
      "qualification": "N/A",
      "lastDate": "24 June 2026",
      "link": "https://www.sarkariresult.app/bmc-pharmacist-technician-and-more-posts/",
      "scrapedAt": "2026-06-21 10:02:46"
    },
    {
      "source": "SarkariResult",
      "title": "UPSSSC Lower PCS Recruitment 2026 Out – Apply Online 2587 Clerk, Executive",
      "posts": "Officer Posts",
      "qualification": "N/A",
      "lastDate": "25 June 2026",
      "link": "https://www.sarkariresult.app/upsssc-lower-pcs-recruitment-2026-out-apply-online-2285-clerk-executive-officer-posts/",
      "scrapedAt": "2026-06-21 10:02:46"
    },
    {
      "source": "SarkariResult",
      "title": "NIT Hamirpur Recruitment 2026 – Research Assistant, Field Investigator",
      "posts": "Walk in",
      "qualification": "N/A",
      "lastDate": "30 June 2026",
      "link": "https://www.sarkariresult.app/nit-hamirpur-recruitment-2026/",
      "scrapedAt": "2026-06-21 10:02:46"
    },
    {
      "source": "SarkariResult",
      "title": "OPTCL Management Trainee Recruitment 2026 Through GATE Out – Apply Online",
      "posts": "60 Posts",
      "qualification": "N/A",
      "lastDate": "25 June 2026",
      "link": "https://www.sarkariresult.app/optcl-mt-advt-no-mppr-03-2024-25-apply-online/",
      "scrapedAt": "2026-06-21 10:02:46"
    },
    {
      "source": "SarkariResult",
      "title": "AIIMS Deoghar Non Faculty Recruitment 2026 – Apply Now",
      "posts": "19 Posts",
      "qualification": "N/A",
      "lastDate": "3 July 2026",
      "link": "https://www.sarkariresult.app/aiims-deoghar-non-faculty-job/",
      "scrapedAt": "2026-06-21 10:02:46"
    },
    {
      "source": "SarkariResult",
      "title": "Aadhaar Supervisor/Operator Recruitment 2026 – Apply For District-wise Vacancies in",
      "posts": "Multiple States",
      "qualification": "N/A",
      "lastDate": "20 June 2026",
      "link": "https://www.sarkariresult.app/aadhaar-seva-kendra-ask-in-various-districts/",
      "scrapedAt": "2026-06-21 10:02:46"
    },
    {
      "source": "SarkariResult",
      "title": "OSSC CGL Specialist Recruitment Exam 2026 Notification Out for 199 Posts",
      "posts": "Apply Online",
      "qualification": "N/A",
      "lastDate": "11 July 2026",
      "link": "https://www.sarkariresult.app/ossc-cgl-recruitment/",
      "scrapedAt": "2026-06-21 10:02:46"
    },
    {
      "source": "SarkariResult",
      "title": "OSSC FSO Recruitment 2026 Out – Apply Online 84 Food Safety",
      "posts": "Officer Posts",
      "qualification": "N/A",
      "lastDate": "8 July 2026",
      "link": "https://www.sarkariresult.app/ossc-fso-2026/",
      "scrapedAt": "2026-06-21 10:02:46"
    },
    {
      "source": "SarkariResult",
      "title": "Punjab & Sind Bank Apprentice Recruitment 2026 Out Apply Online",
      "posts": "635 Posts",
      "qualification": "N/A",
      "lastDate": "",
      "link": "https://www.sarkariresult.app/punjab-sind-bank-apprentice-2024/",
      "scrapedAt": "2026-06-21 10:02:46"
    },
    {
      "source": "SarkariResult",
      "title": "CDAC Recruitment 2026 Notification Out – Apply Online 951 Project Engineer & Manager",
      "posts": "Various Posts",
      "qualification": "N/A",
      "lastDate": "20 June 2026",
      "link": "https://www.sarkariresult.app/cdac-recruitment/",
      "scrapedAt": "2026-06-21 10:02:46"
    },
    {
      "source": "SarkariResult",
      "title": "BRO Recruitment Notification 01/2026 Out for 899",
      "posts": "GREF Posts",
      "qualification": "N/A",
      "lastDate": "4 July 2026",
      "link": "https://www.sarkariresult.app/border-roads-organisation-recruitment/",
      "scrapedAt": "2026-06-21 10:02:46"
    },
    {
      "source": "SarkariResult",
      "title": "IISER Kolkata Faculty Recruitment 2026 Out – Apply Online 27 Assistant",
      "posts": "Professor Posts",
      "qualification": "N/A",
      "lastDate": "30 June 2026",
      "link": "https://www.sarkariresult.app/iiser-kolkata-faculty-recruitment/",
      "scrapedAt": "2026-06-21 10:02:46"
    },
    {
      "source": "SarkariResult",
      "title": "IIA UDC Recruitment 2026 – Apply Online Upper Division",
      "posts": "Clerk Posts",
      "qualification": "N/A",
      "lastDate": "29 June 2026",
      "link": "https://www.sarkariresult.app/indian-institute-of-astrophysics-iia/",
      "scrapedAt": "2026-06-21 10:02:46"
    },
    {
      "source": "SarkariResult",
      "title": "CSIR CEERI Technical Officer & Technician Recruitment 2026 Out –",
      "posts": "Apply Online",
      "qualification": "N/A",
      "lastDate": "20 June 2026",
      "link": "https://www.sarkariresult.app/ceeri-recruitment/",
      "scrapedAt": "2026-06-21 10:02:46"
    },
    {
      "source": "SarkariResult",
      "title": "Allahabad High Court RO ARO Recruitment 2026 OUT – Apply Online 543 Asst Review Officer, Computer",
      "posts": "Assistant Posts",
      "qualification": "N/A",
      "lastDate": "21 June 2026",
      "link": "https://www.sarkariresult.app/allahabad-high-court-ro-aro-recruitment/",
      "scrapedAt": "2026-06-21 10:02:46"
    },
    {
      "source": "SarkariResult",
      "title": "NIOT Recruitment 2026 – Apply Online 19 Project Engineer, Technical Associate and",
      "posts": "More Posts",
      "qualification": "N/A",
      "lastDate": "24 June 2026",
      "link": "https://www.sarkariresult.app/niot-recruitment-2026/",
      "scrapedAt": "2026-06-21 10:02:46"
    },
    {
      "source": "SarkariResult",
      "title": "District and Subordinate Court Tiruvallur Law Officer Recruitment 2026 – Apply",
      "posts": "34 Posts",
      "qualification": "N/A",
      "lastDate": "24 June 2026",
      "link": "https://www.sarkariresult.app/district-and-subordinate-court-tiruvallur/",
      "scrapedAt": "2026-06-21 10:02:46"
    },
    {
      "source": "SarkariResult",
      "title": "Andaman and Nicobar Administration CHSL Recruitment 2026 – Apply Online 716 Depot Clerk,",
      "posts": "Storekeeper Posts",
      "qualification": "N/A",
      "lastDate": "5 July 2026",
      "link": "https://www.sarkariresult.app/andaman-and-nicobar-administration-chsl-recruitment/",
      "scrapedAt": "2026-06-21 10:02:46"
    },
    {
      "source": "SarkariResult",
      "title": "Haryana Kaushal Rozgar Nigam Recruitment 2026 Apply Now HKRN",
      "posts": "Various Posts",
      "qualification": "N/A",
      "lastDate": "",
      "link": "https://www.sarkariresult.app/haryana-kaushal-rozgar-nigam-recruitment-apply-now/",
      "scrapedAt": "2026-06-21 10:02:46"
    },
    {
      "source": "SarkariResult",
      "title": "Bellary DCC Bank Recruitment 2026 OUT – Apply Online 82 JA, Driver and",
      "posts": "More Posts",
      "qualification": "N/A",
      "lastDate": "30 June 2026",
      "link": "https://www.sarkariresult.app/bellary-dcc-bank-recruitment/",
      "scrapedAt": "2026-06-21 10:02:46"
    },
    {
      "source": "SarkariResult",
      "title": "AP TET 2026 June Online Form Begins, Check Notification, Exam",
      "posts": "Date, Eligibility",
      "qualification": "N/A",
      "lastDate": "5 July 2026",
      "link": "https://www.sarkariresult.app/ap-tet-2026-june/",
      "scrapedAt": "2026-06-21 10:02:46"
    },
    {
      "source": "SarkariResult",
      "title": "Mumbai Port Authority Professional Interns Recruitment 2026 Out – Apply",
      "posts": "28 Posts",
      "qualification": "N/A",
      "lastDate": "29 June 2026",
      "link": "https://www.sarkariresult.app/mumbai-port-authority/",
      "scrapedAt": "2026-06-21 10:02:46"
    },
    {
      "source": "SarkariResult",
      "title": "RPSC Senior Scientific Officer Recruitment 2026 Out –",
      "posts": "Online Form",
      "qualification": "N/A",
      "lastDate": "10 July 2026",
      "link": "https://www.sarkariresult.app/rpsc-senior-scientific-officer-recruitment/",
      "scrapedAt": "2026-06-21 10:02:46"
    },
    {
      "source": "SarkariResult",
      "title": "KEA AO AAO Recruitment 2026 Out – Apply Online 945 Assistant Agriculture",
      "posts": "Officer Posts",
      "qualification": "N/A",
      "lastDate": "20 June 2026",
      "link": "https://www.sarkariresult.app/kea-ao-aao-recruitment/",
      "scrapedAt": "2026-06-21 10:02:46"
    },
    {
      "source": "SarkariResult",
      "title": "NCL Electrical Supervisor Recruitment 2026 – Apply Now",
      "posts": "20 Posts",
      "qualification": "N/A",
      "lastDate": "23 June 2026",
      "link": "https://www.sarkariresult.app/ncl-electrical-supervisor-recruitment/",
      "scrapedAt": "2026-06-21 10:02:46"
    },
    {
      "source": "SarkariResult",
      "title": "RPSC School Lecturer (Special) Recruitment 2026 Out – Apply Online",
      "posts": "121 Posts",
      "qualification": "N/A",
      "lastDate": "30 June 2026",
      "link": "https://www.sarkariresult.app/rpsc-school-lecturer-advt-no-19-2024-25/",
      "scrapedAt": "2026-06-21 10:02:46"
    },
    {
      "source": "SarkariResult",
      "title": "BSNL General Manager Recruitment 2026 OUT – Apply Online",
      "posts": "15 Posts",
      "qualification": "N/A",
      "lastDate": "24 June 2026",
      "link": "https://www.sarkariresult.app/bsnl-general-manager-recruitment-2026/",
      "scrapedAt": "2026-06-21 10:02:46"
    },
    {
      "source": "SarkariResult",
      "title": "MSC Bank Managers Recruitment 2026 – Apply Now 36 Specialized Branch Managers,",
      "posts": "Managers Posts",
      "qualification": "N/A",
      "lastDate": "22 June 2026",
      "link": "https://www.sarkariresult.app/msc-bank-managers-recruitment/",
      "scrapedAt": "2026-06-21 10:02:46"
    },
    {
      "source": "SarkariResult",
      "title": "Bihar Police ASI (Technical) Recruitment 2026 Out – Apply Online",
      "posts": "22 Posts",
      "qualification": "N/A",
      "lastDate": "21 June 2026",
      "link": "https://www.sarkariresult.app/bihar-police-asi-technical-recruitment-2026/",
      "scrapedAt": "2026-06-21 10:02:46"
    },
    {
      "source": "SarkariResult",
      "title": "DRDO DESIDOC Apprentice Recruitment 2026 – Apply Online",
      "posts": "20 Posts",
      "qualification": "N/A",
      "lastDate": "1 July 2026",
      "link": "https://www.sarkariresult.app/drdo-desidoc/",
      "scrapedAt": "2026-06-21 10:02:46"
    },
    {
      "source": "SarkariResult",
      "title": "Kerala PSC Recruitment 2026 – Apply Online 59 Lower Division Typist, Office Attendant and",
      "posts": "More Posts",
      "qualification": "N/A",
      "lastDate": "1 July 2026",
      "link": "https://www.sarkariresult.app/kerala-psc-recruitment-2026-apply-online-59-lower-division-typist-office-attendant-and-more-posts/",
      "scrapedAt": "2026-06-21 10:02:46"
    },
    {
      "source": "SarkariResult",
      "title": "SFIO Recruitment 2026 – 38 Joint Director, Deputy Director &",
      "posts": "Other Posts",
      "qualification": "N/A",
      "lastDate": "29 July 2026",
      "link": "https://www.sarkariresult.app/sfio-recruitment-offline-form/",
      "scrapedAt": "2026-06-21 10:02:46"
    },
    {
      "source": "SarkariResult",
      "title": "NIT Srinagar Temporary Faculty Recruitment 2026 – Apply",
      "posts": "80+ Posts",
      "qualification": "N/A",
      "lastDate": "28 June 2026",
      "link": "https://www.sarkariresult.app/nit-srinagar-temporary-faculty-recruitment-2026/",
      "scrapedAt": "2026-06-21 10:02:46"
    },
    {
      "source": "SarkariResult",
      "title": "Himachal Pradesh Jal Shakti Vibhag Recruitment 2026 – Apply 40 Para Pump Operator, Multipurpose",
      "posts": "Worker Posts",
      "qualification": "N/A",
      "lastDate": "27 June 2026",
      "link": "https://www.sarkariresult.app/himachal-pradesh-jal-shakti-vibhag/",
      "scrapedAt": "2026-06-21 10:02:46"
    },
    {
      "source": "SarkariResult",
      "title": "Bharat Petroleum Mid-Senior Level Recruitment 2026 Out –",
      "posts": "Apply Online",
      "qualification": "N/A",
      "lastDate": "20 June 2026",
      "link": "https://www.sarkariresult.app/bharat-petroleum/",
      "scrapedAt": "2026-06-21 10:02:46"
    },
    {
      "source": "SarkariResult",
      "title": "HPPTCL Trainee Driver Recruitment 2026 OUT –",
      "posts": "Apply Now",
      "qualification": "N/A",
      "lastDate": "30 June 2026",
      "link": "https://www.sarkariresult.app/hpptcl-trainee-driver-recruitment/",
      "scrapedAt": "2026-06-21 10:02:46"
    },
    {
      "source": "SarkariResult",
      "title": "HAL Koraput Trade Apprentice Recruitment 2026 –",
      "posts": "Apply Form",
      "qualification": "N/A",
      "lastDate": "30 June 2026",
      "link": "https://www.sarkariresult.app/hal-koraput-trade-apprentice-recruitment/",
      "scrapedAt": "2026-06-21 10:02:46"
    },
    {
      "source": "SarkariResult",
      "title": "ISSA Paid Internship Recruitment 2026 – Apply Online",
      "posts": "25 Posts",
      "qualification": "N/A",
      "lastDate": "20 June 2026",
      "link": "https://www.sarkariresult.app/issa-paid-internship-recruitment-2026-apply-online-25-posts/",
      "scrapedAt": "2026-06-21 10:02:46"
    },
    {
      "source": "SarkariResult",
      "title": "MDL Trade Apprentice Recruitment 2026 – Apply Online 495 Seats Across",
      "posts": "18 Trades",
      "qualification": "N/A",
      "lastDate": "1 July 2026",
      "link": "https://www.sarkariresult.app/mdl-trade-apprentice-recruitment/",
      "scrapedAt": "2026-06-21 10:02:46"
    },
    {
      "source": "SarkariResult",
      "title": "Sainik School Goalpara Recruitment 2026 – Apply Now 17 Teaching and Non",
      "posts": "Teaching Posts",
      "qualification": "N/A",
      "lastDate": "25 June 2026",
      "link": "https://www.sarkariresult.app/sainik-school-goalpara-notification/",
      "scrapedAt": "2026-06-21 10:02:46"
    },
    {
      "source": "SarkariResult",
      "title": "AMMB Recruitment 2026 – Apply Online Peon,",
      "posts": "Watchman Posts",
      "qualification": "N/A",
      "lastDate": "3 July 2026",
      "link": "https://www.sarkariresult.app/ammb-recruitment/",
      "scrapedAt": "2026-06-21 10:02:46"
    },
    {
      "source": "SarkariResult",
      "title": "UPSSSC UP Vidhan Bhawan Guard / Fire Guard Recruitment 2026 Out – Online Apply",
      "posts": "170 Posts",
      "qualification": "N/A",
      "lastDate": "29 June 2026",
      "link": "https://www.sarkariresult.app/upsssc-up-vidhan-bhawan-guard-fire-guard-recruitment-2026/",
      "scrapedAt": "2026-06-21 10:02:46"
    },
    {
      "source": "SarkariResult",
      "title": "HPPSC Assistant Professor Recruitment 2026 – Apply Online",
      "posts": "37 Posts",
      "qualification": "N/A",
      "lastDate": "4 July 2026",
      "link": "https://www.sarkariresult.app/hppsc-assistant-professor-recruitment-2026-apply-online-37-posts/",
      "scrapedAt": "2026-06-21 10:02:46"
    },
    {
      "source": "SarkariResult",
      "title": "Andaman and Nicobar Combined Matric Level Exam 2026 Notice Out – Apply Online 1535 Group",
      "posts": "C Posts",
      "qualification": "N/A",
      "lastDate": "28 June 2026",
      "link": "https://www.sarkariresult.app/andaman-and-nicobar-combined-matric-level-exam-2026/",
      "scrapedAt": "2026-06-21 10:02:46"
    },
    {
      "source": "SarkariResult",
      "title": "JIPMER Senior Resident Recruitment 2026 Out – Apply Online",
      "posts": "89 Posts",
      "qualification": "N/A",
      "lastDate": "29 June 2026",
      "link": "https://www.sarkariresult.app/jipmer-senior-resident-recruitment/",
      "scrapedAt": "2026-06-21 10:02:46"
    },
    {
      "source": "SarkariResult",
      "title": "ECHS Chennai Recruitment 2026 Out – Apply Now 80 Chowkidar, Safaiwala and",
      "posts": "More Posts",
      "qualification": "N/A",
      "lastDate": "11 July 2026",
      "link": "https://www.sarkariresult.app/echs-chennai/",
      "scrapedAt": "2026-06-21 10:02:46"
    },
    {
      "source": "SarkariResult",
      "title": "Lakshmibai College Delhi Non-Teaching Staff Recruitment 2026 – Apply Online 24 Assistant,",
      "posts": "JA Posts",
      "qualification": "N/A",
      "lastDate": "11 July 2026",
      "link": "https://www.sarkariresult.app/lakshmibai-college-delhi-non-teaching-staff-recruitment-2026-apply-online-24-assistant-ja-posts/",
      "scrapedAt": "2026-06-21 10:02:46"
    },
    {
      "source": "SarkariResult",
      "title": "SSC CGL 2026 Notification Out for 12256 Vacancies, Apply Online",
      "posts": "Direct Link",
      "qualification": "N/A",
      "lastDate": "22 June 2026",
      "link": "https://www.sarkariresult.app/ssc-cgl-2026/",
      "scrapedAt": "2026-06-21 10:02:46"
    },
    {
      "source": "SarkariResult",
      "title": "UT Administration of Dadra and Nagar Haveli and Daman and Diu Recruitment 2026 Walk In",
      "posts": "60 Posts",
      "qualification": "N/A",
      "lastDate": "25 June 2026",
      "link": "https://www.sarkariresult.app/ut-administration-of-dadra-and-nagar-haveli-and-daman-and-diu-recruitment-2026-walk-in-60-posts/",
      "scrapedAt": "2026-06-21 10:02:46"
    },
    {
      "source": "SarkariResult",
      "title": "Punjab and Haryana High Court Clerk Recruitment 2026 Out – Apply Online for",
      "posts": "1265 Posts",
      "qualification": "N/A",
      "lastDate": "9 July 2026",
      "link": "https://www.sarkariresult.app/punjab-haryana-high-court-clerk-recruitment/",
      "scrapedAt": "2026-06-21 10:02:46"
    },
    {
      "source": "SarkariResult",
      "title": "IIT Guwahati Sports Instructors Recruitment 2026 – Walk in",
      "posts": "26 Posts",
      "qualification": "N/A",
      "lastDate": "24 June 2026",
      "link": "https://www.sarkariresult.app/iit-guwahati-sports-instructors-recruitment/",
      "scrapedAt": "2026-06-21 10:02:46"
    },
    {
      "source": "SarkariResult",
      "title": "IIT Delhi Faculty Recruitment 2026 – Apply Online Asst & Associate",
      "posts": "Professor Posts",
      "qualification": "N/A",
      "lastDate": "30 June 2026",
      "link": "https://www.sarkariresult.app/iit-delhi-faculty-recruitment-2026-apply-online-asst-associate-professor-posts/",
      "scrapedAt": "2026-06-21 10:02:46"
    },
    {
      "source": "SarkariResult",
      "title": "UPSSSC Vidhan Bhawan Guard / Fire Guard Recruitment 2026 Out – Apply Online",
      "posts": "170 Posts",
      "qualification": "N/A",
      "lastDate": "29 June 2026",
      "link": "https://www.sarkariresult.app/upsssc-vidhan-bhawan-guard-fire-guard-recruitment-2026-out-apply-online-179-posts/",
      "scrapedAt": "2026-06-21 10:02:46"
    },
    {
      "source": "SarkariResult",
      "title": "CSIR-NIScPR Recruitment 2026 – Walk in 15 Project Assistant, Project Scientist and",
      "posts": "More Posts",
      "qualification": "N/A",
      "lastDate": "30 June 2026",
      "link": "https://www.sarkariresult.app/csir-niscpr-recruitment/",
      "scrapedAt": "2026-06-21 10:02:46"
    },
    {
      "source": "SarkariResult",
      "title": "CTET September 2026 Correction / Edit",
      "posts": "Form Link",
      "qualification": "N/A",
      "lastDate": "",
      "link": "https://www.sarkariresult.app/ctet-september-2026/",
      "scrapedAt": "2026-06-21 10:02:46"
    },
    {
      "source": "SarkariResult",
      "title": "OPSC OCS Answer Key 2026 Out Check GS Paper 1 & CSAT PDF and",
      "posts": "Raise Objection",
      "qualification": "N/A",
      "lastDate": "",
      "link": "https://www.sarkariresult.app/opsc-ocs-answer-key-2026/",
      "scrapedAt": "2026-06-21 10:02:46"
    },
    {
      "source": "SarkariResult",
      "title": "Hindustan Shipyard HSL Recruitment 2026 – Apply Online 34 Manager, Dy Project Officer and",
      "posts": "More Posts",
      "qualification": "N/A",
      "lastDate": "24 June 2026",
      "link": "https://www.sarkariresult.app/hindustan-shipyard-hsl-recruitment/",
      "scrapedAt": "2026-06-21 10:02:46"
    },
    {
      "source": "SarkariResult",
      "title": "CGPSC Sahayak Jila Lok Abhiyojan Adhikari Recruitment 2026 – Apply Online",
      "posts": "15 Posts",
      "qualification": "N/A",
      "lastDate": "21 July 2026",
      "link": "https://www.sarkariresult.app/cgpsc-sahayak-jila-lok-abhiyojan-adhikari-recruitment-2026/",
      "scrapedAt": "2026-06-21 10:02:46"
    },
    {
      "source": "SarkariResult",
      "title": "ISRO URSC JRF Recruitment 2026 – Apply Online 17 Junior Research",
      "posts": "Fellow Posts",
      "qualification": "N/A",
      "lastDate": "11 July 2026",
      "link": "https://www.sarkariresult.app/isro-ursc-jrf-recruitment-2026-apply-online-17-junior-research-fellow-posts/",
      "scrapedAt": "2026-06-21 10:02:46"
    },
    {
      "source": "SarkariResult",
      "title": "IMD Recruitment 2026 – Apply Online 12 Administrative and Scientific",
      "posts": "Consultants Posts",
      "qualification": "N/A",
      "lastDate": "7 July 2026",
      "link": "https://www.sarkariresult.app/imd-recruitment-2026/",
      "scrapedAt": "2026-06-21 10:02:46"
    },
    {
      "source": "SarkariResult",
      "title": "Surat Municipal Corporation (SMC) Recruitment 2026 – Apply Online",
      "posts": "120 Posts",
      "qualification": "N/A",
      "lastDate": "6 July 2026",
      "link": "https://www.sarkariresult.app/surat-municipal-corporation-smc-recruitment-2026-apply-online-120-posts/",
      "scrapedAt": "2026-06-21 10:02:46"
    },
    {
      "source": "SarkariResult",
      "title": "NHSRCL Recruitment 2026 Out Apply For 209 DE &",
      "posts": "JE Posts",
      "qualification": "N/A",
      "lastDate": "14 July 2026",
      "link": "https://www.sarkariresult.app/nhsrcl-recruitment-2026-out-apply-for-209-de-je-posts/",
      "scrapedAt": "2026-06-21 10:02:46"
    },
    {
      "source": "SarkariResult",
      "title": "NILERD Recruitment 2026 – Apply Online 13 Joint Director, Deputy and Assistant",
      "posts": "Director Posts",
      "qualification": "N/A",
      "lastDate": "45 Days",
      "link": "https://www.sarkariresult.app/nilerd-recruitment/",
      "scrapedAt": "2026-06-21 10:02:46"
    },
    {
      "source": "SarkariResult",
      "title": "KVAFSU Teaching Recruitment 2026 – Apply Online 96 Associate and Assistant",
      "posts": "Professor Posts",
      "qualification": "N/A",
      "lastDate": "20 June 2026",
      "link": "https://www.sarkariresult.app/kvafsu-recruitment/",
      "scrapedAt": "2026-06-21 10:02:46"
    },
    {
      "source": "SarkariResult",
      "title": "DCHS Kakinada Recruitment 2026 – Walk in 34 Civil Asst. Surgeon General and",
      "posts": "Specialists Posts",
      "qualification": "N/A",
      "lastDate": "20 June 2026",
      "link": "https://www.sarkariresult.app/dchs-kakinada-recruitment/",
      "scrapedAt": "2026-06-21 10:02:46"
    },
    {
      "source": "SarkariResult",
      "title": "CIL Management Trainee Recruitment 2026 (New) – Apply Online",
      "posts": "660 Posts",
      "qualification": "N/A",
      "lastDate": "21 June 2026",
      "link": "https://www.sarkariresult.app/coal-india-recruitment/",
      "scrapedAt": "2026-06-21 10:02:46"
    },
    {
      "source": "SarkariResult",
      "title": "BFUHS Pharmacist Recruitment 2026 Notification Out – Apply Online",
      "posts": "454 Posts",
      "qualification": "N/A",
      "lastDate": "1 July 2026",
      "link": "https://www.sarkariresult.app/bfuhs-pharmacist-recruitment/",
      "scrapedAt": "2026-06-21 10:02:46"
    },
    {
      "source": "SarkariResult",
      "title": "ICMR BMHRC Recruitment 2026 – Apply Online 16 Professor, Asst Professor and",
      "posts": "More Posts",
      "qualification": "N/A",
      "lastDate": "14 July 2026",
      "link": "https://www.sarkariresult.app/icmr-bmhrc/",
      "scrapedAt": "2026-06-21 10:02:46"
    },
    {
      "source": "SarkariResult",
      "title": "LNIPE NERC Guwahati Non-Teaching Recruitment 2026 – Apply Online 18",
      "posts": "+ Posts",
      "qualification": "N/A",
      "lastDate": "20 June 2026",
      "link": "https://www.sarkariresult.app/lnipe-nerc-guwahati-non-teaching-recruitment-2026-apply-online-18-posts/",
      "scrapedAt": "2026-06-21 10:02:46"
    },
    {
      "source": "SarkariResult",
      "title": "TN PWD Apprentice Recruitment 2026 Notification Out – Apply Online",
      "posts": "760 Posts",
      "qualification": "N/A",
      "lastDate": "25 June 2026",
      "link": "https://www.sarkariresult.app/tn-pwd-apprentice-recruitment-2026-notification-out/",
      "scrapedAt": "2026-06-21 10:02:46"
    },
    {
      "source": "SarkariResult",
      "title": "DHS Tiruppur Recruitment 2026 – Apply Now 97 Hospital Worker, Staff Nurse and",
      "posts": "More Posts",
      "qualification": "N/A",
      "lastDate": "29 June 2026",
      "link": "https://www.sarkariresult.app/dhs-tiruppur-recruitment-2026-apply-now-97-hospital-worker-staff-nurse-and-more-posts/",
      "scrapedAt": "2026-06-21 10:02:46"
    },
    {
      "source": "SarkariResult",
      "title": "SMVDSB Recruitment 2026 Notification Out – Apply Now 105 Junior Assistant, Storekeeper and",
      "posts": "More Posts",
      "qualification": "N/A",
      "lastDate": "7 July 2026",
      "link": "https://www.sarkariresult.app/smvdsb-recruitment-2026-notification-out-apply-now-105-junior-assistant-storekeeper-and-more-posts/",
      "scrapedAt": "2026-06-21 10:02:46"
    },
    {
      "source": "SarkariResult",
      "title": "Sundargarh District Court Recruitment 2026 – Apply Now 19 Junior Typist, Steno",
      "posts": "Various Posts",
      "qualification": "N/A",
      "lastDate": "13 July 2026",
      "link": "https://www.sarkariresult.app/sundargarh-district-court/",
      "scrapedAt": "2026-06-21 10:02:46"
    },
    {
      "source": "SarkariResult",
      "title": "District Collector Office Ranipet Law Officer Recruitment 2026 – Apply Now",
      "posts": "11 Posts",
      "qualification": "N/A",
      "lastDate": "2 July 2026",
      "link": "https://www.sarkariresult.app/ranipet-law-officer-recruitment-2026-out/",
      "scrapedAt": "2026-06-21 10:02:46"
    },
    {
      "source": "SarkariResult",
      "title": "CUTN Recruitment 2026 – Apply Now Consultant, Junior",
      "posts": "Engineer Posts",
      "qualification": "N/A",
      "lastDate": "26 June 2026",
      "link": "https://www.sarkariresult.app/cutn-consultant-junior-engineer-posts/",
      "scrapedAt": "2026-06-21 10:02:46"
    },
    {
      "source": "SarkariResult",
      "title": "Collector Guest Teacher Recruitment 2026 – Apply Online",
      "posts": "60 Posts",
      "qualification": "N/A",
      "lastDate": "21 June 2026",
      "link": "https://www.sarkariresult.app/collector-guest-teacher-recruitment/",
      "scrapedAt": "2026-06-21 10:02:46"
    },
    {
      "source": "SarkariResult",
      "title": "Bombay High Court Cook-cum-Attendant Recruitment 2026 –",
      "posts": "Apply Now",
      "qualification": "N/A",
      "lastDate": "6 July 2026",
      "link": "https://www.sarkariresult.app/bombay-high-court-cook-cum-attendant-recruitment/",
      "scrapedAt": "2026-06-21 10:02:46"
    },
    {
      "source": "SarkariResult",
      "title": "DCPU Katihar Support Person Recruitment 2026 – Apply Form",
      "posts": "10 Posts",
      "qualification": "N/A",
      "lastDate": "21 June 2026",
      "link": "https://www.sarkariresult.app/dcpu-katihar-support-person-recruitment/",
      "scrapedAt": "2026-06-21 10:02:46"
    },
    {
      "source": "SarkariResult",
      "title": "Gurugram University Assistant Professor Recruitment 2026 – Apply Online",
      "posts": "17 Posts",
      "qualification": "N/A",
      "lastDate": "25 June 2026",
      "link": "https://www.sarkariresult.app/gurugram-university-assistant-professor-recruitment/",
      "scrapedAt": "2026-06-21 10:02:46"
    },
    {
      "source": "SarkariResult",
      "title": "IIT Goa Graduate Apprentice Recruitment 2026 – Walk in",
      "posts": "12 Posts",
      "qualification": "N/A",
      "lastDate": "30 June 2026",
      "link": "https://www.sarkariresult.app/iit-goa-graduate-apprentice-recruitment-2026-walk-in-12-posts/",
      "scrapedAt": "2026-06-21 10:02:46"
    },
    {
      "source": "SarkariResult",
      "title": "BEL Educational Institutions BEEI Teacher Recruitment 2026 – Apply Online",
      "posts": "34 Posts",
      "qualification": "N/A",
      "lastDate": "7 July 2026",
      "link": "https://www.sarkariresult.app/bel-educational-institutions-beei-teacher-recruitment-2026-apply-online-34-posts/",
      "scrapedAt": "2026-06-21 10:02:46"
    },
    {
      "source": "SarkariResult",
      "title": "GSSSB X-Ray Technician Class 3 Recruitment 2026 –  Apply Online",
      "posts": "246 Posts",
      "qualification": "N/A",
      "lastDate": "29 June 2026",
      "link": "https://www.sarkariresult.app/gsssb-x-ray-technician-class-3-recruitment-2026/",
      "scrapedAt": "2026-06-21 10:02:46"
    },
    {
      "source": "SarkariResult",
      "title": "APSC Drilling Engineer Recruitment 2026 Out – Apply Online",
      "posts": "01 Post",
      "qualification": "N/A",
      "lastDate": "23 July 2026",
      "link": "https://www.sarkariresult.app/apsc-drilling-engineer-recruitment-2026/",
      "scrapedAt": "2026-06-21 10:02:46"
    },
    {
      "source": "SarkariResult",
      "title": "Ganjam District Court Recruitment 2026 – Apply Online 67 Stenographer, Junior Typist and",
      "posts": "More Posts",
      "qualification": "N/A",
      "lastDate": "18 July 2026",
      "link": "https://www.sarkariresult.app/ganjam-court-steno-junior-typist-posts/",
      "scrapedAt": "2026-06-21 10:02:46"
    },
    {
      "source": "SarkariResult",
      "title": "RGIPT Superintendent Grade-I (Accounts) Recruitment 2026 – Apply Online",
      "posts": "01 Post",
      "qualification": "N/A",
      "lastDate": "15 July 2026",
      "link": "https://www.sarkariresult.app/rgipt-superintendent-grade-i-accounts-recruitment-2026/",
      "scrapedAt": "2026-06-21 10:02:46"
    },
    {
      "source": "SarkariResult",
      "title": "Pithoragarh Homeguards Recruitment 2026 OUT – Apply Now",
      "posts": "22 Posts",
      "qualification": "N/A",
      "lastDate": "30 June 2026",
      "link": "https://www.sarkariresult.app/pithoragarh-homeguards-recruitment/",
      "scrapedAt": "2026-06-21 10:02:46"
    },
    {
      "source": "SarkariResult",
      "title": "NSUT Teaching and Non Teaching Recruitment 2026 – Apply Online 61",
      "posts": "Various Posts",
      "qualification": "N/A",
      "lastDate": "30 June 2026",
      "link": "https://www.sarkariresult.app/nsut-recruitment/",
      "scrapedAt": "2026-06-21 10:02:46"
    },
    {
      "source": "SarkariResult",
      "title": "RGIPT Training and Placement Officer Recruitment 2026 –",
      "posts": "Online Form",
      "qualification": "N/A",
      "lastDate": "15 July 2026",
      "link": "https://www.sarkariresult.app/rgipt/",
      "scrapedAt": "2026-06-21 10:02:46"
    },
    {
      "source": "SarkariResult",
      "title": "Rajasthan State Eligibility Test SET Online Form 2026",
      "posts": "Direct Link",
      "qualification": "N/A",
      "lastDate": "15 July 2026",
      "link": "https://www.sarkariresult.app/rajasthan-state-eligibility-test-set/",
      "scrapedAt": "2026-06-21 10:02:46"
    },
    {
      "source": "SarkariResult",
      "title": "AIIMS CRE-5 Recruitment 2026 – Apply Online 1484 Group B &",
      "posts": "C Posts",
      "qualification": "N/A",
      "lastDate": "30 June 2026",
      "link": "https://www.sarkariresult.app/aiims-cre-5-recruitment/",
      "scrapedAt": "2026-06-21 10:02:46"
    },
    {
      "source": "SarkariResult",
      "title": "HAL Lucknow ITI Apprentices Recruitment 2026 Out –",
      "posts": "Online Form",
      "qualification": "N/A",
      "lastDate": "30 June 2026",
      "link": "https://www.sarkariresult.app/hal-lucknow-iti-apprentices-recruitment-2026-out-online-form/",
      "scrapedAt": "2026-06-21 10:02:46"
    },
    {
      "source": "SarkariResult",
      "title": "GUVNL Vidyut Sahayak (Junior Engineer – Electrical) Recruitment 2026 –  Apply Online",
      "posts": "183 Posts",
      "qualification": "N/A",
      "lastDate": "2 July 2026",
      "link": "https://www.sarkariresult.app/guvnl-and-its-subsidiary-companies/",
      "scrapedAt": "2026-06-21 10:02:46"
    },
    {
      "source": "SarkariResult",
      "title": "BFUHS Recruitment 2026 – Apply Online Asst Landscape Officer, Accountant",
      "posts": "07 Posts",
      "qualification": "N/A",
      "lastDate": "28 June 2026",
      "link": "https://www.sarkariresult.app/bfuhs-recruitment-2026/",
      "scrapedAt": "2026-06-21 10:02:46"
    },
    {
      "source": "SarkariResult",
      "title": "RSSB Senior & Basic Computer Instructor Recruitment 2026 Out – Apply Online",
      "posts": "3951 Posts",
      "qualification": "N/A",
      "lastDate": "23 June 2026",
      "link": "https://www.sarkariresult.app/rsmssb-computer-instructor-recruitment/",
      "scrapedAt": "2026-06-21 10:02:46"
    },
    {
      "source": "SarkariResult",
      "title": "Indian Navy 10+2 B.Tech Cadet Entry Scheme Jan 2027 Notice Out – Apply Online",
      "posts": "60 Posts",
      "qualification": "N/A",
      "lastDate": "29 June 2026",
      "link": "https://www.sarkariresult.app/indian-navy-102-b-tech-cadet-entry-scheme-jan-2027/",
      "scrapedAt": "2026-06-21 10:02:46"
    },
    {
      "source": "SarkariResult",
      "title": "UKMSSB Nursing Officer Recruitment 2026 – Apply Online",
      "posts": "196 Posts",
      "qualification": "N/A",
      "lastDate": "2 July 2026",
      "link": "https://www.sarkariresult.app/ukmssb-nursing-officer-recruitment/",
      "scrapedAt": "2026-06-21 10:02:46"
    },
    {
      "source": "SarkariResult",
      "title": "Indian Air Force AFCAT 02/2026 Recruitment 2026 Out –",
      "posts": "Apply Online",
      "qualification": "N/A",
      "lastDate": "21 June 2026",
      "link": "https://www.sarkariresult.app/indian-air-force-recruitment/",
      "scrapedAt": "2026-06-21 10:02:46"
    },
    {
      "source": "SarkariResult",
      "title": "Mumbai University CEBS Faculty Recruitment 2026 – Apply 14 Reader, Assistant & Associate",
      "posts": "Professor Posts",
      "qualification": "N/A",
      "lastDate": "15 July 2026",
      "link": "https://www.sarkariresult.app/mumbai-university-cebs-faculty-recruitment/",
      "scrapedAt": "2026-06-21 10:02:46"
    },
    {
      "source": "SarkariResult",
      "title": "ECHS Recruitment 2026 – Apply Now 10 Peon, Driver and",
      "posts": "More Posts",
      "qualification": "N/A",
      "lastDate": "10 July 2026",
      "link": "https://www.sarkariresult.app/echs-recruitment-2026-apply-now-10-peon-driver-and-more-posts/",
      "scrapedAt": "2026-06-21 10:02:46"
    },
    {
      "source": "SarkariResult",
      "title": "CG Vyapam O.T. Technician Recruitment 2026 – Apply Online",
      "posts": "15 Posts",
      "qualification": "N/A",
      "lastDate": "3 July 2026",
      "link": "https://www.sarkariresult.app/cg-vyapam-o-t-technician-recruitment-2026-apply-online-15-posts/",
      "scrapedAt": "2026-06-21 10:02:46"
    },
    {
      "source": "SarkariResult",
      "title": "ABV-IIITM Gwalior Recruitment 2026 – Apply 10 Various",
      "posts": "Non-Teaching Posts",
      "qualification": "N/A",
      "lastDate": "29 June 2026",
      "link": "https://www.sarkariresult.app/?p=315668",
      "scrapedAt": "2026-06-21 10:02:46"
    },
    {
      "source": "SarkariResult",
      "title": "RRB ALP Recruitment 2026 Out (CEN 01/2026) Correction Form Link for",
      "posts": "11127 Posts",
      "qualification": "N/A",
      "lastDate": "",
      "link": "https://www.sarkariresult.app/rrb-alp-recruitment-2026-out-cen-01-2026-notification-out-apply-online-11127-posts/",
      "scrapedAt": "2026-06-21 10:02:46"
    },
    {
      "source": "SarkariResult",
      "title": "DSWO Etawah Subject Specialist Recruitment 2026 – Apply Form",
      "posts": "21 Posts",
      "qualification": "N/A",
      "lastDate": "20 June 2026",
      "link": "https://www.sarkariresult.app/dswo-etawah/",
      "scrapedAt": "2026-06-21 10:02:46"
    },
    {
      "source": "SarkariResult",
      "title": "NCLT Recruitment 2026 – Apply Now 106 Staff Car Driver, UDC and",
      "posts": "More Posts",
      "qualification": "N/A",
      "lastDate": "20 July 2026",
      "link": "https://www.sarkariresult.app/nclt-recruitment/",
      "scrapedAt": "2026-06-21 10:02:46"
    },
    {
      "source": "SarkariResult",
      "title": "ICAR IISWC Recruitment 2026 – Apply Now 16 Assistant and Lower Division",
      "posts": "Clerk Posts",
      "qualification": "N/A",
      "lastDate": "20 June 2026",
      "link": "https://www.sarkariresult.app/icar-iiswc-recruitment/",
      "scrapedAt": "2026-06-21 10:02:46"
    },
    {
      "source": "SarkariResult",
      "title": "GSSSB Recruitment 2026 – Apply 25 Female Health Worker",
      "posts": "(Class-3) Posts",
      "qualification": "N/A",
      "lastDate": "20 June 2026",
      "link": "https://www.sarkariresult.app/gsssb-female-health-worker-jobs/",
      "scrapedAt": "2026-06-21 10:02:46"
    },
    {
      "source": "SarkariResult",
      "title": "CMHO Mungeli Recruitment 2026 – Apply Online 106 Attendant, Staff Nurse and",
      "posts": "More Posts",
      "qualification": "N/A",
      "lastDate": "20 June 2026",
      "link": "https://www.sarkariresult.app/cmho-mungeli-recruitment-2026-apply-online-106-attendant-staff-nurse-and-more-posts/",
      "scrapedAt": "2026-06-21 10:02:46"
    },
    {
      "source": "SarkariResult",
      "title": "DRDO RCI Paid Internship Recruitment 2026 – Apply Now",
      "posts": "160 Posts",
      "qualification": "N/A",
      "lastDate": "20 June 2026",
      "link": "https://www.sarkariresult.app/drdo-rci-paid-internship-recruitment-2026-apply-now-160-posts/",
      "scrapedAt": "2026-06-21 10:02:46"
    },
    {
      "source": "SarkariResult",
      "title": "Allahabad High Court Research Associates Recruitment 2026 – Apply Online",
      "posts": "RA Posts",
      "qualification": "N/A",
      "lastDate": "20 June 2026",
      "link": "https://www.sarkariresult.app/allahabad-high-court-research-associates-recruitment/",
      "scrapedAt": "2026-06-21 10:02:46"
    },
    {
      "source": "SarkariResult",
      "title": "HPPSC Physiotherapist Recruitment 2026 OUT – Apply Online",
      "posts": "05 Posts",
      "qualification": "N/A",
      "lastDate": "6 July 2026",
      "link": "https://www.sarkariresult.app/hppsc-physiotherapist-recruitment-2026-out-apply-online-05-posts/",
      "scrapedAt": "2026-06-21 10:02:46"
    },
    {
      "source": "SarkariResult",
      "title": "District Subordinate Court Madurai Law Officers Recruitment 2026 – Apply Now",
      "posts": "31 Posts",
      "qualification": "N/A",
      "lastDate": "29 June 2026",
      "link": "https://www.sarkariresult.app/district-subordinate-court-madurai/",
      "scrapedAt": "2026-06-21 10:02:46"
    },
    {
      "source": "SarkariResult",
      "title": "DBEO Kushinagar Teaching and Non Teaching Recruitment 2026 – Apply 29 Peon, PGT and",
      "posts": "More Posts",
      "qualification": "N/A",
      "lastDate": "20 June 2026",
      "link": "https://www.sarkariresult.app/dbeo-kushinagar/",
      "scrapedAt": "2026-06-21 10:02:46"
    },
    {
      "source": "SarkariResult",
      "title": "GSSSB Jamadar Recruitment 2026 –",
      "posts": "Online Form",
      "qualification": "N/A",
      "lastDate": "",
      "link": "https://www.sarkariresult.app/gsssb-jamadar-2026/",
      "scrapedAt": "2026-06-21 10:02:46"
    },
    {
      "source": "SarkariResult",
      "title": "Navy 10+2 B.Tech Entry January 2027 Batch Apply Online",
      "posts": "60 Posts",
      "qualification": "N/A",
      "lastDate": "",
      "link": "https://www.sarkariresult.app/navy-102-b-tech-entry-january-2027/",
      "scrapedAt": "2026-06-21 10:02:46"
    },
    {
      "source": "SarkariResult",
      "title": "GSSSB Surveyor Recruitment 2026 Notification Out – Apply Online",
      "posts": "47 Posts",
      "qualification": "N/A",
      "lastDate": "26 June 2026",
      "link": "https://www.sarkariresult.app/gsssb-notification/",
      "scrapedAt": "2026-06-21 10:02:46"
    },
    {
      "source": "SarkariResult",
      "title": "Assam University Teaching Recruitment 2026 – Apply Online 123 Professor, Asst",
      "posts": "Professor Posts",
      "qualification": "N/A",
      "lastDate": "10 July 2026",
      "link": "https://www.sarkariresult.app/assam-university-teaching-recruitment-2026/",
      "scrapedAt": "2026-06-21 10:02:46"
    },
    {
      "source": "SarkariResult",
      "title": "JNU PG Admission 2026 Application Form Direct Link Eligibility Check Admission",
      "posts": "Process Date",
      "qualification": "N/A",
      "lastDate": "15th June 2026",
      "link": "https://www.sarkariresult.app/jnu-pg-admission/",
      "scrapedAt": "2026-06-21 10:02:46"
    },
    {
      "source": "SarkariResult",
      "title": "Sainik School Ghorakhal Recruitment 2026 – Teaching & Non-Teaching",
      "posts": "10 Posts",
      "qualification": "N/A",
      "lastDate": "21 Days",
      "link": "https://www.sarkariresult.app/sainik-school-ghorakhal-recruitment-2026/",
      "scrapedAt": "2026-06-21 10:02:46"
    },
    {
      "source": "SarkariResult",
      "title": "OSSSC Nursing Officer Recruitment 2026 OUT – Apply Online",
      "posts": "5989 Posts",
      "qualification": "N/A",
      "lastDate": "3 July 2026",
      "link": "https://www.sarkariresult.app/osssc-nursing-officer-recruitment-2026/",
      "scrapedAt": "2026-06-21 10:02:46"
    },
    {
      "source": "SarkariResult",
      "title": "Korea District NHM Recruitment 2026 Out – Apply Online",
      "posts": "140 Posts",
      "qualification": "N/A",
      "lastDate": "3 July 2026",
      "link": "https://www.sarkariresult.app/korea-district-nhm-recruitment/",
      "scrapedAt": "2026-06-21 10:02:46"
    },
    {
      "source": "SarkariResult",
      "title": "UPSC Geo Scientist 2025 Mains Admit Card 2026 Out for 85 Post",
      "posts": "Check Here",
      "qualification": "N/A",
      "lastDate": "",
      "link": "https://www.sarkariresult.app/upsc-geo-scientist-2025/",
      "scrapedAt": "2026-06-21 10:02:46"
    },
    {
      "source": "SarkariResult",
      "title": "TSPSC AEE Recruitment 2026 OUT – Apply Online 222 Asst Executive",
      "posts": "Engineer Posts",
      "qualification": "N/A",
      "lastDate": "13 July 2026",
      "link": "https://www.sarkariresult.app/tgpsc-assistant-executive-engineer-recruitment/",
      "scrapedAt": "2026-06-21 10:02:46"
    },
    {
      "source": "SarkariResult",
      "title": "CRPF Commandant Recruitment 2026 – Walk",
      "posts": "in Interview",
      "qualification": "N/A",
      "lastDate": "30 July 2026",
      "link": "https://www.sarkariresult.app/crpf-commandant-recruitment/",
      "scrapedAt": "2026-06-21 10:02:46"
    },
    {
      "source": "SarkariResult",
      "title": "Annapurna Yojana (or Annapurna Bhandar Scheme) – Eligibility, How to Apply, Benefits &",
      "posts": "Status Check",
      "qualification": "N/A",
      "lastDate": "",
      "link": "https://www.sarkariresult.app/annapurna-yojana/",
      "scrapedAt": "2026-06-21 10:02:46"
    },
    {
      "source": "SarkariResult",
      "title": "Andaman & Nicobar Police Recruitment 2026 Out – Apply Online",
      "posts": "495 Posts",
      "qualification": "N/A",
      "lastDate": "22 June 2026",
      "link": "https://www.sarkariresult.app/andaman-nicobar-police-recruitment-2026-out-apply-online-495-posts/",
      "scrapedAt": "2026-06-21 10:02:46"
    },
    {
      "source": "SarkariResult",
      "title": "CUSAT Security Guard Recruitment 2026 – Apply Online",
      "posts": "22 Posts",
      "qualification": "N/A",
      "lastDate": "3 July 2026",
      "link": "https://www.sarkariresult.app/cusat-security-guard-recruitment-2026-apply-online-22-posts/",
      "scrapedAt": "2026-06-21 10:02:46"
    },
    {
      "source": "SarkariResult",
      "title": "TGPSC AEE Electrical Recruitment 2026 OUT –",
      "posts": "Apply Online",
      "qualification": "N/A",
      "lastDate": "",
      "link": "https://www.sarkariresult.app/tgpsc-aee-electrical-recruitment-2026-out-apply-online/",
      "scrapedAt": "2026-06-21 10:02:46"
    },
    {
      "source": "SarkariResult",
      "title": "UPSSSC Auditor / Assistant Accountant Recruitment 2026 OUT – Apply Online",
      "posts": "1829 Posts",
      "qualification": "N/A",
      "lastDate": "3 August 2026",
      "link": "https://www.sarkariresult.app/upsssc-auditor-assistant-accountant-recruitment/",
      "scrapedAt": "2026-06-21 10:02:46"
    },
    {
      "source": "SarkariResult",
      "title": "Delhi Anganwadi Recruitment 2026 – Apply Now 62 Assistant cum DEO, Accountant and",
      "posts": "More Posts",
      "qualification": "N/A",
      "lastDate": "11 July 2026",
      "link": "https://www.sarkariresult.app/delhi-anganwadi-online-form/",
      "scrapedAt": "2026-06-21 10:02:46"
    },
    {
      "source": "SarkariResult",
      "title": "Delhi DPCC Trainee Recruitment 2026 Out for 150 Technical & Scientific",
      "posts": "Trainee Posts",
      "qualification": "N/A",
      "lastDate": "21 Days",
      "link": "https://www.sarkariresult.app/delhi-dpcc-trainee-recruitment/",
      "scrapedAt": "2026-06-21 10:02:46"
    },
    {
      "source": "SarkariResult",
      "title": "Air Force Group C (Civilian) Posts Recruitment 2026 – LDC, Driver",
      "posts": "47 Posts",
      "qualification": "N/A",
      "lastDate": "",
      "link": "https://www.sarkariresult.app/iaf-group-c-civilian-recruitment-2026-out-apply-47-ldc-typist-driver-posts/",
      "scrapedAt": "2026-06-21 10:02:46"
    },
    {
      "source": "SarkariResult",
      "title": "Assam Cooperative Apex Bank Assistant Admit Card 2026 Download Exam Date Out for",
      "posts": "150 Posts",
      "qualification": "N/A",
      "lastDate": "",
      "link": "https://www.sarkariresult.app/assam-cooperative-apex-bank-assistant-recruitment-2026-out-apply-online-150-posts/",
      "scrapedAt": "2026-06-21 10:02:46"
    },
    {
      "source": "SarkariResult",
      "title": "KMF GUMUL Recruitment 2026 – Apply Online 55 Junior Technician, Assistant",
      "posts": "Manager Posts",
      "qualification": "N/A",
      "lastDate": "27 June 2026",
      "link": "https://www.sarkariresult.app/kmf-gumul-recruitment/",
      "scrapedAt": "2026-06-21 10:02:46"
    },
    {
      "source": "SarkariResult",
      "title": "College of Defence Management Recruitment 2026 – Apply Now MTS, Steno and",
      "posts": "More Posts",
      "qualification": "N/A",
      "lastDate": "30 Days",
      "link": "https://www.sarkariresult.app/college-of-defence-management/",
      "scrapedAt": "2026-06-21 10:02:46"
    },
    {
      "source": "SarkariResult",
      "title": "SSC Stenographer Grade C & D Vacancy Details 2026 OUT",
      "posts": "Check Here",
      "qualification": "N/A",
      "lastDate": "",
      "link": "https://www.sarkariresult.app/ssc-stenographer-notification/",
      "scrapedAt": "2026-06-21 10:02:46"
    },
    {
      "source": "SarkariResult",
      "title": "Oil India Recruitment 2026 – Apply Online 10 Economist, Deputy Chief Engineer and",
      "posts": "More Posts",
      "qualification": "N/A",
      "lastDate": "28 June 2026",
      "link": "https://www.sarkariresult.app/oil-india-economist-deputy-chief-engineer-vacancy/",
      "scrapedAt": "2026-06-21 10:02:46"
    },
    {
      "source": "SarkariResult",
      "title": "TNPSC CTS Exam Notification 2026 Out – Apply Online For 461 Non",
      "posts": "Interview Posts",
      "qualification": "N/A",
      "lastDate": "25 June 2026",
      "link": "https://www.sarkariresult.app/tnpsc-cts-exam-notification/",
      "scrapedAt": "2026-06-21 10:02:46"
    },
    {
      "source": "SarkariResult",
      "title": "EMRS Pakur Guest Teacher Recruitment 2026 – Apply Now",
      "posts": "20 Posts",
      "qualification": "N/A",
      "lastDate": "",
      "link": "https://www.sarkariresult.app/emrs-pakur/",
      "scrapedAt": "2026-06-21 10:02:46"
    },
    {
      "source": "SarkariResult",
      "title": "Collectorate Rayagada Recruitment 2026 – Apply Now Launch Driver,",
      "posts": "Khalasi Posts",
      "qualification": "N/A",
      "lastDate": "",
      "link": "https://www.sarkariresult.app/collectorate-rayagada/",
      "scrapedAt": "2026-06-21 10:02:46"
    },
    {
      "source": "SarkariResult",
      "title": "Meghalaya PSC Recruitment 2026 – Apply Online 13 Fishery Officer & Jr Football",
      "posts": "Coach Posts",
      "qualification": "N/A",
      "lastDate": "25 June 2026",
      "link": "https://www.sarkariresult.app/meghalaya-psc/",
      "scrapedAt": "2026-06-21 10:02:46"
    },
    {
      "source": "SarkariResult",
      "title": "NPCIL MAPS Apprentices Recruitment 2026 – Apply Now 158 Trade, Diploma and Graduate",
      "posts": "Apprentices Posts",
      "qualification": "N/A",
      "lastDate": "30 June 2026",
      "link": "https://www.sarkariresult.app/nuclear-power-corporation-of-india-limited-npcil/",
      "scrapedAt": "2026-06-21 10:02:46"
    }
  ]
}